{"generatedAt":"2026-07-19T18:10:29.228Z","locations":{"hayama":{"generatedAt":"2026-07-19T18:10:31.307Z","tide":{"tideName":"小潮","moonAge":5,"highs":[{"time":"08:05","level":136},{"time":"21:04","level":141}],"lows":[{"time":"02:24","level":71},{"time":"14:31","level":43}],"advice":"本日は小潮。満潮08:05・干潮02:24を目安に行動を。"},"timeline":[{"key":"2026-07-20T03:00","hour":3,"label":"03:00","dateLabel":"7/20","isNight":true,"yahoo":{"icon":"☀️","desc":"晴れ","temp":26,"rainMm":0,"pop":0,"windDir":"南南西","windDeg":202.5,"windArrow":"↗️","windSpeed":3,"windAlert":""},"umikaisei":{"wave":0.5,"waveFromFallback":false,"windDir":"南南西","windDeg":202.5,"windArrow":"↗️","windSpeed":6.2,"windAlert":"(面荒れ注意・オンショア)","tide":73,"tideTrend":"up"},"windy":{"wave":0.46,"wavePeriod":5.85,"windDir":"南南西","windDeg":192,"windArrow":"⬆️","windSpeed":1.94,"windAlert":""},"gfs":{"windDir":"南南西","windDeg":195,"windArrow":"⬆️","windSpeed":2.28,"windAlert":""},"tideBadge":null},{"key":"2026-07-20T04:00","hour":4,"label":"04:00","dateLabel":"7/20","isNight":true,"yahoo":{"icon":"☀️","desc":"晴れ","temp":26,"rainMm":0,"pop":0,"windDir":"南南西","windDeg":202.5,"windArrow":"↗️","windSpeed":3,"windAlert":""},"umikaisei":{"wave":0.5,"waveFromFallback":false,"windDir":"南南西","windDeg":202.5,"windArrow":"↗️","windSpeed":5.6,"windAlert":"(面荒れ注意・オンショア)","tide":83,"tideTrend":"up"},"windy":{"wave":0.44,"wavePeriod":5.95,"windDir":"南","windDeg":191,"windArrow":"⬆️","windSpeed":1.63,"windAlert":""},"gfs":{"windDir":"南南西","windDeg":199,"windArrow":"⬆️","windSpeed":2.12,"windAlert":""},"tideBadge":null},{"key":"2026-07-20T05:00","hour":5,"label":"05:00","dateLabel":"7/20","isNight":false,"yahoo":{"icon":"☀️","desc":"晴れ","temp":26,"rainMm":0,"pop":0,"windDir":"南南西","windDeg":202.5,"windArrow":"↗️","windSpeed":3,"windAlert":""},"umikaisei":{"wave":0.5,"waveFromFallback":false,"windDir":"南西","windDeg":225,"windArrow":"↗️","windSpeed":4.6,"windAlert":"","tide":99,"tideTrend":"up"},"windy":{"wave":0.44,"wavePeriod":6.05,"windDir":"南","windDeg":184,"windArrow":"⬆️","windSpeed":1.4,"windAlert":""},"gfs":{"windDir":"南南西","windDeg":198,"windArrow":"⬆️","windSpeed":1.99,"windAlert":""},"tideBadge":null},{"key":"2026-07-20T06:00","hour":6,"label":"06:00","dateLabel":"7/20","isNight":false,"yahoo":{"icon":"☀️","desc":"晴れ","temp":27,"rainMm":0,"pop":0,"windDir":"南南西","windDeg":202.5,"windArrow":"↗️","windSpeed":2,"windAlert":""},"umikaisei":{"wave":0.4,"waveFromFallback":false,"windDir":"南西","windDeg":225,"windArrow":"↗️","windSpeed":3.2,"windAlert":"","tide":116,"tideTrend":"up"},"windy":{"wave":0.42,"wavePeriod":6.1,"windDir":"南","windDeg":180,"windArrow":"⬆️","windSpeed":1.3,"windAlert":""},"gfs":{"windDir":"南南西","windDeg":197,"windArrow":"⬆️","windSpeed":1.68,"windAlert":""},"tideBadge":null},{"key":"2026-07-20T07:00","hour":7,"label":"07:00","dateLabel":"7/20","isNight":false,"yahoo":{"icon":"☀️","desc":"晴れ","temp":27,"rainMm":0,"pop":0,"windDir":"南南西","windDeg":202.5,"windArrow":"↗️","windSpeed":2,"windAlert":""},"umikaisei":{"wave":0.4,"waveFromFallback":false,"windDir":"西南西","windDeg":247.5,"windArrow":"➡️","windSpeed":1.6,"windAlert":"","tide":130,"tideTrend":"up"},"windy":{"wave":0.42,"wavePeriod":6.15,"windDir":"南","windDeg":187,"windArrow":"⬆️","windSpeed":1.71,"windAlert":""},"gfs":{"windDir":"南南西","windDeg":195,"windArrow":"⬆️","windSpeed":1.14,"windAlert":""},"tideBadge":null},{"key":"2026-07-20T08:00","hour":8,"label":"08:00","dateLabel":"7/20","isNight":false,"yahoo":{"icon":"☀️","desc":"晴れ","temp":27,"rainMm":0,"pop":0,"windDir":"南南西","windDeg":202.5,"windArrow":"↗️","windSpeed":2,"windAlert":""},"umikaisei":{"wave":0.4,"waveFromFallback":false,"windDir":"南西","windDeg":225,"windArrow":"↗️","windSpeed":1.3,"windAlert":"","tide":136,"tideTrend":"down"},"windy":{"wave":0.4,"wavePeriod":6.2,"windDir":"南南西","windDeg":195,"windArrow":"⬆️","windSpeed":1.96,"windAlert":""},"gfs":{"windDir":"南南東","windDeg":162,"windArrow":"⬆️","windSpeed":1.26,"windAlert":""},"tideBadge":"🛑 満潮間近"},{"key":"2026-07-20T09:00","hour":9,"label":"09:00","dateLabel":"7/20","isNight":false,"yahoo":{"icon":"☀️","desc":"晴れ","temp":31,"rainMm":0,"pop":0,"windDir":"南南西","windDeg":202.5,"windArrow":"↗️","windSpeed":2,"windAlert":""},"umikaisei":{"wave":0.4,"waveFromFallback":false,"windDir":"南南西","windDeg":202.5,"windArrow":"↗️","windSpeed":2,"windAlert":"","tide":131,"tideTrend":"down"},"windy":{"wave":0.4,"wavePeriod":6.25,"windDir":"南南西","windDeg":197,"windArrow":"⬆️","windSpeed":2.09,"windAlert":""},"gfs":{"windDir":"南","windDeg":172,"windArrow":"⬆️","windSpeed":2.12,"windAlert":""},"tideBadge":null},{"key":"2026-07-20T10:00","hour":10,"label":"10:00","dateLabel":"7/20","isNight":false,"yahoo":{"icon":"☀️","desc":"晴れ","temp":31,"rainMm":0,"pop":0,"windDir":"南南西","windDeg":202.5,"windArrow":"↗️","windSpeed":2,"windAlert":""},"umikaisei":{"wave":0.4,"waveFromFallback":false,"windDir":"南南西","windDeg":202.5,"windArrow":"↗️","windSpeed":3.5,"windAlert":"","tide":118,"tideTrend":"down"},"windy":{"wave":0.4,"wavePeriod":6.3,"windDir":"南南西","windDeg":195,"windArrow":"⬆️","windSpeed":2.38,"windAlert":""},"gfs":{"windDir":"南","windDeg":180,"windArrow":"⬆️","windSpeed":2.6,"windAlert":""},"tideBadge":null},{"key":"2026-07-20T11:00","hour":11,"label":"11:00","dateLabel":"7/20","isNight":false,"yahoo":{"icon":"☀️","desc":"晴れ","temp":31,"rainMm":0,"pop":0,"windDir":"南南西","windDeg":202.5,"windArrow":"↗️","windSpeed":2,"windAlert":""},"umikaisei":{"wave":0.4,"waveFromFallback":false,"windDir":"南南西","windDeg":202.5,"windArrow":"↗️","windSpeed":4.7,"windAlert":"","tide":97,"tideTrend":"down"},"windy":{"wave":0.4,"wavePeriod":6.35,"windDir":"南南西","windDeg":194,"windArrow":"⬆️","windSpeed":2.89,"windAlert":""},"gfs":{"windDir":"南","windDeg":182,"windArrow":"⬆️","windSpeed":3.3,"windAlert":""},"tideBadge":null},{"key":"2026-07-20T12:00","hour":12,"label":"12:00","dateLabel":"7/20","isNight":false,"yahoo":{"icon":"☀️","desc":"晴れ","temp":32,"rainMm":0,"pop":0,"windDir":"南南西","windDeg":202.5,"windArrow":"↗️","windSpeed":3,"windAlert":""},"umikaisei":{"wave":0.4,"waveFromFallback":false,"windDir":"南南西","windDeg":202.5,"windArrow":"↗️","windSpeed":6.1,"windAlert":"(面荒れ注意・オンショア)","tide":75,"tideTrend":"down"},"windy":{"wave":0.4,"wavePeriod":6.3,"windDir":"南南西","windDeg":192,"windArrow":"⬆️","windSpeed":3.37,"windAlert":""},"gfs":{"windDir":"南","windDeg":186,"windArrow":"⬆️","windSpeed":4.02,"windAlert":""},"tideBadge":null},{"key":"2026-07-20T13:00","hour":13,"label":"13:00","dateLabel":"7/20","isNight":false,"yahoo":{"icon":"☀️","desc":"晴れ","temp":32,"rainMm":0,"pop":7,"windDir":"南南西","windDeg":202.5,"windArrow":"↗️","windSpeed":3,"windAlert":""},"umikaisei":{"wave":0.4,"waveFromFallback":false,"windDir":"南南西","windDeg":202.5,"windArrow":"↗️","windSpeed":6.6,"windAlert":"(面荒れ注意・オンショア)","tide":56,"tideTrend":"down"},"windy":{"wave":0.4,"wavePeriod":6.1,"windDir":"南南西","windDeg":192,"windArrow":"⬆️","windSpeed":3.88,"windAlert":""},"gfs":{"windDir":"南","windDeg":188,"windArrow":"⬆️","windSpeed":4.44,"windAlert":""},"tideBadge":null},{"key":"2026-07-20T14:00","hour":14,"label":"14:00","dateLabel":"7/20","isNight":false,"yahoo":{"icon":"☀️","desc":"晴れ","temp":32,"rainMm":0,"pop":16,"windDir":"南南西","windDeg":202.5,"windArrow":"↗️","windSpeed":3,"windAlert":""},"umikaisei":{"wave":0.5,"waveFromFallback":false,"windDir":"南南西","windDeg":202.5,"windArrow":"↗️","windSpeed":6.9,"windAlert":"(面荒れ注意・オンショア)","tide":45,"tideTrend":null},"windy":{"wave":0.42,"wavePeriod":5.85,"windDir":"南南西","windDeg":196,"windArrow":"⬆️","windSpeed":4.37,"windAlert":""},"gfs":{"windDir":"南","windDeg":189,"windArrow":"⬆️","windSpeed":4.65,"windAlert":""},"tideBadge":"🟢 干潮間近"},{"key":"2026-07-20T15:00","hour":15,"label":"15:00","dateLabel":"7/20","isNight":false,"yahoo":{"icon":"☀️","desc":"晴れ","temp":32,"rainMm":0,"pop":20,"windDir":"南","windDeg":180,"windArrow":"⬆️","windSpeed":4,"windAlert":""},"umikaisei":{"wave":0.5,"waveFromFallback":false,"windDir":"南南西","windDeg":202.5,"windArrow":"↗️","windSpeed":6.8,"windAlert":"(面荒れ注意・オンショア)","tide":45,"tideTrend":"up"},"windy":{"wave":0.42,"wavePeriod":5.6,"windDir":"南南西","windDeg":201,"windArrow":"⬆️","windSpeed":4.49,"windAlert":""},"gfs":{"windDir":"南南西","windDeg":195,"windArrow":"⬆️","windSpeed":4.75,"windAlert":""},"tideBadge":null},{"key":"2026-07-20T16:00","hour":16,"label":"16:00","dateLabel":"7/20","isNight":false,"yahoo":{"icon":"☀️","desc":"晴れ","temp":32,"rainMm":0,"pop":16,"windDir":"南","windDeg":180,"windArrow":"⬆️","windSpeed":4,"windAlert":""},"umikaisei":{"wave":0.6,"waveFromFallback":false,"windDir":"南南西","windDeg":202.5,"windArrow":"↗️","windSpeed":7.1,"windAlert":"(面荒れ注意・オンショア)","tide":55,"tideTrend":"up"},"windy":{"wave":0.44,"wavePeriod":5.35,"windDir":"南南西","windDeg":196,"windArrow":"⬆️","windSpeed":4.37,"windAlert":""},"gfs":{"windDir":"南南西","windDeg":192,"windArrow":"⬆️","windSpeed":4.39,"windAlert":""},"tideBadge":null},{"key":"2026-07-20T17:00","hour":17,"label":"17:00","dateLabel":"7/20","isNight":false,"yahoo":{"icon":"☀️","desc":"晴れ","temp":32,"rainMm":0,"pop":7,"windDir":"南","windDeg":180,"windArrow":"⬆️","windSpeed":4,"windAlert":""},"umikaisei":{"wave":0.6,"waveFromFallback":false,"windDir":"南南西","windDeg":202.5,"windArrow":"↗️","windSpeed":7.8,"windAlert":"(面荒れ注意・オンショア)","tide":74,"tideTrend":"up"},"windy":{"wave":0.46,"wavePeriod":5.05,"windDir":"南南西","windDeg":196,"windArrow":"⬆️","windSpeed":3.96,"windAlert":""},"gfs":{"windDir":"南","windDeg":188,"windArrow":"⬆️","windSpeed":5.15,"windAlert":"(面荒れ注意・オンショア)"},"tideBadge":null},{"key":"2026-07-20T18:00","hour":18,"label":"18:00","dateLabel":"7/20","isNight":false,"yahoo":{"icon":"☀️","desc":"晴れ","temp":29,"rainMm":0,"pop":0,"windDir":"南","windDeg":180,"windArrow":"⬆️","windSpeed":4,"windAlert":""},"umikaisei":{"wave":0.7,"waveFromFallback":false,"windDir":"南南西","windDeg":202.5,"windArrow":"↗️","windSpeed":7.7,"windAlert":"(面荒れ注意・オンショア)","tide":97,"tideTrend":"up"},"windy":{"wave":0.48,"wavePeriod":4.9,"windDir":"南","windDeg":191,"windArrow":"⬆️","windSpeed":3.57,"windAlert":""},"gfs":{"windDir":"南","windDeg":187,"windArrow":"⬆️","windSpeed":4.23,"windAlert":""},"tideBadge":null},{"key":"2026-07-20T19:00","hour":19,"label":"19:00","dateLabel":"7/20","isNight":false,"yahoo":{"icon":"☀️","desc":"晴れ","temp":29,"rainMm":0,"pop":0,"windDir":"南","windDeg":180,"windArrow":"⬆️","windSpeed":4,"windAlert":""},"umikaisei":{"wave":0.7,"waveFromFallback":false,"windDir":"南南西","windDeg":202.5,"windArrow":"↗️","windSpeed":7.5,"windAlert":"(面荒れ注意・オンショア)","tide":119,"tideTrend":"up"},"windy":{"wave":0.48,"wavePeriod":4.85,"windDir":"南","windDeg":189,"windArrow":"⬆️","windSpeed":3.14,"windAlert":""},"gfs":{"windDir":"南","windDeg":180,"windArrow":"⬆️","windSpeed":3,"windAlert":""},"tideBadge":null},{"key":"2026-07-20T20:00","hour":20,"label":"20:00","dateLabel":"7/20","isNight":false,"yahoo":{"icon":"☀️","desc":"晴れ","temp":29,"rainMm":0,"pop":0,"windDir":"南","windDeg":180,"windArrow":"⬆️","windSpeed":4,"windAlert":""},"umikaisei":{"wave":0.7,"waveFromFallback":false,"windDir":"南南西","windDeg":202.5,"windArrow":"↗️","windSpeed":7.2,"windAlert":"(面荒れ注意・オンショア)","tide":135,"tideTrend":"up"},"windy":{"wave":0.48,"wavePeriod":4.95,"windDir":"南南西","windDeg":193,"windArrow":"⬆️","windSpeed":2.77,"windAlert":""},"gfs":{"windDir":"南","windDeg":189,"windArrow":"⬆️","windSpeed":2.53,"windAlert":""},"tideBadge":null},{"key":"2026-07-20T21:00","hour":21,"label":"21:00","dateLabel":"7/20","isNight":false,"yahoo":{"icon":"☀️","desc":"晴れ","temp":28,"rainMm":0,"pop":0,"windDir":"南南西","windDeg":202.5,"windArrow":"↗️","windSpeed":4,"windAlert":""},"umikaisei":{"wave":0.7,"waveFromFallback":false,"windDir":"南南西","windDeg":202.5,"windArrow":"↗️","windSpeed":7,"windAlert":"(面荒れ注意・オンショア)","tide":141,"tideTrend":"down"},"windy":{"wave":0.48,"wavePeriod":5,"windDir":"南","windDeg":185,"windArrow":"⬆️","windSpeed":2.31,"windAlert":""},"gfs":{"windDir":"南南西","windDeg":207,"windArrow":"↗️","windSpeed":3.13,"windAlert":""},"tideBadge":"🛑 満潮間近"},{"key":"2026-07-20T22:00","hour":22,"label":"22:00","dateLabel":"7/20","isNight":false,"yahoo":{"icon":"☀️","desc":"晴れ","temp":28,"rainMm":0,"pop":0,"windDir":"南南西","windDeg":202.5,"windArrow":"↗️","windSpeed":4,"windAlert":""},"umikaisei":{"wave":0.7,"waveFromFallback":false,"windDir":"南南西","windDeg":202.5,"windArrow":"↗️","windSpeed":7,"windAlert":"(面荒れ注意・オンショア)","tide":136,"tideTrend":"down"},"windy":{"wave":0.48,"wavePeriod":5.05,"windDir":"南","windDeg":185,"windArrow":"⬆️","windSpeed":2.21,"windAlert":""},"gfs":{"windDir":"南南西","windDeg":200,"windArrow":"⬆️","windSpeed":3.29,"windAlert":""},"tideBadge":null},{"key":"2026-07-20T23:00","hour":23,"label":"23:00","dateLabel":"7/20","isNight":false,"yahoo":{"icon":"☀️","desc":"晴れ","temp":28,"rainMm":0,"pop":0,"windDir":"南南西","windDeg":202.5,"windArrow":"↗️","windSpeed":4,"windAlert":""},"umikaisei":{"wave":0.6,"waveFromFallback":false,"windDir":"南南西","windDeg":202.5,"windArrow":"↗️","windSpeed":6.8,"windAlert":"(面荒れ注意・オンショア)","tide":123,"tideTrend":"down"},"windy":{"wave":0.46,"wavePeriod":5.15,"windDir":"南","windDeg":188,"windArrow":"⬆️","windSpeed":2.22,"windAlert":""},"gfs":{"windDir":"南南西","windDeg":197,"windArrow":"⬆️","windSpeed":3.13,"windAlert":""},"tideBadge":null},{"key":"2026-07-21T00:00","hour":0,"label":"00:00","dateLabel":"7/21","isNight":true,"yahoo":{"icon":"☀️","desc":"晴れ","temp":27,"rainMm":0,"pop":0,"windDir":"南南西","windDeg":202.5,"windArrow":"↗️","windSpeed":3,"windAlert":""},"umikaisei":{"wave":0.6,"waveFromFallback":false,"windDir":"南南西","windDeg":202.5,"windArrow":"↗️","windSpeed":6.9,"windAlert":"(面荒れ注意・オンショア)","tide":104,"tideTrend":"down"},"windy":{"wave":0.46,"wavePeriod":5.2,"windDir":"南","windDeg":191,"windArrow":"⬆️","windSpeed":2.14,"windAlert":""},"gfs":{"windDir":"南南西","windDeg":197,"windArrow":"⬆️","windSpeed":2.82,"windAlert":""},"tideBadge":null},{"key":"2026-07-21T01:00","hour":1,"label":"01:00","dateLabel":"7/21","isNight":true,"yahoo":{"icon":"☀️","desc":"晴れ","temp":27,"rainMm":0,"pop":0,"windDir":"南南西","windDeg":202.5,"windArrow":"↗️","windSpeed":3,"windAlert":""},"umikaisei":{"wave":0.6,"waveFromFallback":false,"windDir":"南南西","windDeg":202.5,"windArrow":"↗️","windSpeed":6.8,"windAlert":"(面荒れ注意・オンショア)","tide":86,"tideTrend":"down"},"windy":{"wave":0.44,"wavePeriod":5.25,"windDir":"南","windDeg":189,"windArrow":"⬆️","windSpeed":1.92,"windAlert":""},"gfs":{"windDir":"南","windDeg":191,"windArrow":"⬆️","windSpeed":2.65,"windAlert":""},"tideBadge":null},{"key":"2026-07-21T02:00","hour":2,"label":"02:00","dateLabel":"7/21","isNight":true,"yahoo":{"icon":"☀️","desc":"晴れ","temp":27,"rainMm":0,"pop":0,"windDir":"南南西","windDeg":202.5,"windArrow":"↗️","windSpeed":3,"windAlert":""},"umikaisei":{"wave":0.6,"waveFromFallback":false,"windDir":"南南西","windDeg":202.5,"windArrow":"↗️","windSpeed":6.8,"windAlert":"(面荒れ注意・オンショア)","tide":71,"tideTrend":"down"},"windy":{"wave":0.44,"wavePeriod":5.3,"windDir":"南","windDeg":190,"windArrow":"⬆️","windSpeed":1.73,"windAlert":""},"gfs":{"windDir":"南","windDeg":191,"windArrow":"⬆️","windSpeed":2.65,"windAlert":""},"tideBadge":"🟢 干潮間近"},{"key":"2026-07-21T03:00","hour":3,"label":"03:00","dateLabel":"7/21","isNight":true,"yahoo":{"icon":"☀️","desc":"晴れ","temp":27,"rainMm":0,"pop":0,"windDir":"南西","windDeg":225,"windArrow":"↗️","windSpeed":2,"windAlert":""},"umikaisei":{"wave":0.6,"waveFromFallback":false,"windDir":"南南西","windDeg":202.5,"windArrow":"↗️","windSpeed":6.7,"windAlert":"(面荒れ注意・オンショア)","tide":65,"tideTrend":"up"},"windy":{"wave":0.42,"wavePeriod":5.35,"windDir":"南","windDeg":188,"windArrow":"⬆️","windSpeed":1.51,"windAlert":""},"gfs":{"windDir":"南","windDeg":185,"windArrow":"⬆️","windSpeed":2.31,"windAlert":""},"tideBadge":null},{"key":"2026-07-21T04:00","hour":4,"label":"04:00","dateLabel":"7/21","isNight":true,"yahoo":{"icon":"☀️","desc":"晴れ","temp":27,"rainMm":0,"pop":0,"windDir":"南西","windDeg":225,"windArrow":"↗️","windSpeed":2,"windAlert":""},"umikaisei":{"wave":0.6,"waveFromFallback":false,"windDir":"南西","windDeg":225,"windArrow":"↗️","windSpeed":6.3,"windAlert":"(面荒れ注意・オンショア)","tide":67,"tideTrend":"up"},"windy":{"wave":0.4,"wavePeriod":5.45,"windDir":"南","windDeg":189,"windArrow":"⬆️","windSpeed":1.32,"windAlert":""},"gfs":{"windDir":"南","windDeg":180,"windArrow":"⬆️","windSpeed":1.9,"windAlert":""},"tideBadge":null},{"key":"2026-07-21T05:00","hour":5,"label":"05:00","dateLabel":"7/21","isNight":false,"yahoo":{"icon":"☀️","desc":"晴れ","temp":27,"rainMm":0,"pop":0,"windDir":"南西","windDeg":225,"windArrow":"↗️","windSpeed":2,"windAlert":""},"umikaisei":{"wave":0.6,"waveFromFallback":false,"windDir":"南西","windDeg":225,"windArrow":"↗️","windSpeed":5.8,"windAlert":"(面荒れ注意・オンショア)","tide":78,"tideTrend":"up"},"windy":{"wave":0.4,"wavePeriod":5.55,"windDir":"南南西","windDeg":193,"windArrow":"⬆️","windSpeed":0.92,"windAlert":""},"gfs":{"windDir":"南","windDeg":175,"windArrow":"⬆️","windSpeed":1.1,"windAlert":""},"tideBadge":null},{"key":"2026-07-21T06:00","hour":6,"label":"06:00","dateLabel":"7/21","isNight":false,"yahoo":{"icon":"☀️","desc":"晴れ","temp":28,"rainMm":0,"pop":0,"windDir":"南西","windDeg":225,"windArrow":"↗️","windSpeed":1,"windAlert":""},"umikaisei":{"wave":0.6,"waveFromFallback":false,"windDir":"南西","windDeg":225,"windArrow":"↗️","windSpeed":4.7,"windAlert":"","tide":94,"tideTrend":"up"},"windy":{"wave":0.38,"wavePeriod":5.65,"windDir":"南","windDeg":180,"windArrow":"⬆️","windSpeed":0.8,"windAlert":""},"gfs":{"windDir":"南南東","windDeg":166,"windArrow":"⬆️","windSpeed":0.82,"windAlert":""},"tideBadge":null},{"key":"2026-07-21T07:00","hour":7,"label":"07:00","dateLabel":"7/21","isNight":false,"yahoo":{"icon":"☀️","desc":"晴れ","temp":28,"rainMm":0,"pop":0,"windDir":"南西","windDeg":225,"windArrow":"↗️","windSpeed":1,"windAlert":""},"umikaisei":{"wave":0.6,"waveFromFallback":false,"windDir":"南西","windDeg":225,"windArrow":"↗️","windSpeed":3.2,"windAlert":"","tide":110,"tideTrend":"up"},"windy":{"wave":0.38,"wavePeriod":5.75,"windDir":"南","windDeg":189,"windArrow":"⬆️","windSpeed":1.22,"windAlert":""},"gfs":{"windDir":"南","windDeg":171,"windArrow":"⬆️","windSpeed":0.61,"windAlert":""},"tideBadge":null},{"key":"2026-07-21T08:00","hour":8,"label":"08:00","dateLabel":"7/21","isNight":false,"yahoo":{"icon":"☀️","desc":"晴れ","temp":28,"rainMm":0,"pop":0,"windDir":"南西","windDeg":225,"windArrow":"↗️","windSpeed":1,"windAlert":""},"umikaisei":{"wave":0.5,"waveFromFallback":false,"windDir":"南西","windDeg":225,"windArrow":"↗️","windSpeed":1.9,"windAlert":"","tide":122,"tideTrend":"up"},"windy":{"wave":0.36,"wavePeriod":5.9,"windDir":"南南西","windDeg":200,"windArrow":"⬆️","windSpeed":2.02,"windAlert":""},"gfs":{"windDir":"南","windDeg":171,"windArrow":"⬆️","windSpeed":0.61,"windAlert":""},"tideBadge":"🛑 満潮間近"},{"key":"2026-07-21T09:00","hour":9,"label":"09:00","dateLabel":"7/21","isNight":false,"yahoo":{"icon":"☀️","desc":"晴れ","temp":31,"rainMm":0,"pop":0,"windDir":"南南西","windDeg":202.5,"windArrow":"↗️","windSpeed":2,"windAlert":""},"umikaisei":{"wave":0.5,"waveFromFallback":false,"windDir":"南南西","windDeg":202.5,"windArrow":"↗️","windSpeed":1.9,"windAlert":"","tide":127,"tideTrend":"down"},"windy":{"wave":0.36,"wavePeriod":6,"windDir":"南南西","windDeg":204,"windArrow":"↗️","windSpeed":2.42,"windAlert":""},"gfs":{"windDir":"南南東","windDeg":164,"windArrow":"⬆️","windSpeed":1.46,"windAlert":""},"tideBadge":null},{"key":"2026-07-21T10:00","hour":10,"label":"10:00","dateLabel":"7/21","isNight":false,"yahoo":{"icon":"☀️","desc":"晴れ","temp":31,"rainMm":0,"pop":7,"windDir":"南南西","windDeg":202.5,"windArrow":"↗️","windSpeed":2,"windAlert":""},"umikaisei":{"wave":0.5,"waveFromFallback":false,"windDir":"南南西","windDeg":202.5,"windArrow":"↗️","windSpeed":3.1,"windAlert":"","tide":123,"tideTrend":"down"},"windy":{"wave":0.36,"wavePeriod":6.05,"windDir":"南南西","windDeg":206,"windArrow":"↗️","windSpeed":2.55,"windAlert":""},"gfs":{"windDir":"南南東","windDeg":157,"windArrow":"↖️","windSpeed":2.06,"windAlert":""},"tideBadge":null},{"key":"2026-07-21T11:00","hour":11,"label":"11:00","dateLabel":"7/21","isNight":false,"yahoo":{"icon":"☀️","desc":"晴れ","temp":31,"rainMm":0,"pop":17,"windDir":"南南西","windDeg":202.5,"windArrow":"↗️","windSpeed":2,"windAlert":""},"umikaisei":{"wave":0.4,"waveFromFallback":false,"windDir":"南南西","windDeg":202.5,"windArrow":"↗️","windSpeed":4.2,"windAlert":"","tide":111,"tideTrend":"down"},"windy":{"wave":0.36,"wavePeriod":6.1,"windDir":"南南西","windDeg":201,"windArrow":"⬆️","windSpeed":2.79,"windAlert":""},"gfs":{"windDir":"南南東","windDeg":165,"windArrow":"⬆️","windSpeed":3.01,"windAlert":""},"tideBadge":null},{"key":"2026-07-21T12:00","hour":12,"label":"12:00","dateLabel":"7/21","isNight":false,"yahoo":{"icon":"☀️","desc":"晴れ","temp":32,"rainMm":0,"pop":31,"windDir":"南南西","windDeg":202.5,"windArrow":"↗️","windSpeed":3,"windAlert":""},"umikaisei":{"wave":0.4,"waveFromFallback":false,"windDir":"南南西","windDeg":202.5,"windArrow":"↗️","windSpeed":5.4,"windAlert":"(面荒れ注意・オンショア)","tide":95,"tideTrend":"down"},"windy":{"wave":0.36,"wavePeriod":6.1,"windDir":"南南西","windDeg":194,"windArrow":"⬆️","windSpeed":3.3,"windAlert":""},"gfs":{"windDir":"南","windDeg":175,"windArrow":"⬆️","windSpeed":3.81,"windAlert":""},"tideBadge":null},{"key":"2026-07-21T13:00","hour":13,"label":"13:00","dateLabel":"7/21","isNight":false,"yahoo":{"icon":"☀️","desc":"晴れ","temp":32,"rainMm":0,"pop":53,"windDir":"南南西","windDeg":202.5,"windArrow":"↗️","windSpeed":3,"windAlert":""},"umikaisei":{"wave":0.4,"waveFromFallback":false,"windDir":"南南西","windDeg":202.5,"windArrow":"↗️","windSpeed":6,"windAlert":"(面荒れ注意・オンショア)","tide":78,"tideTrend":"down"},"windy":{"wave":0.38,"wavePeriod":6,"windDir":"南南西","windDeg":197,"windArrow":"⬆️","windSpeed":3.86,"windAlert":""},"gfs":{"windDir":"南","windDeg":188,"windArrow":"⬆️","windSpeed":4.54,"windAlert":""},"tideBadge":null},{"key":"2026-07-21T14:00","hour":14,"label":"14:00","dateLabel":"7/21","isNight":false,"yahoo":{"icon":"☀️","desc":"晴れ","temp":32,"rainMm":0,"pop":79,"windDir":"南南西","windDeg":202.5,"windArrow":"↗️","windSpeed":3,"windAlert":""},"umikaisei":{"wave":0.5,"waveFromFallback":false,"windDir":"南南西","windDeg":202.5,"windArrow":"↗️","windSpeed":6.3,"windAlert":"(面荒れ注意・オンショア)","tide":65,"tideTrend":"down"},"windy":{"wave":0.38,"wavePeriod":5.8,"windDir":"南南西","windDeg":196,"windArrow":"⬆️","windSpeed":4.37,"windAlert":""},"gfs":{"windDir":"南南西","windDeg":196,"windArrow":"⬆️","windSpeed":4.46,"windAlert":""},"tideBadge":"🟢 干潮間近"},{"key":"2026-07-21T15:00","hour":15,"label":"15:00","dateLabel":"7/21","isNight":false,"yahoo":{"icon":"☀️","desc":"晴れ","temp":32,"rainMm":0,"pop":92,"windDir":"南南西","windDeg":202.5,"windArrow":"↗️","windSpeed":4,"windAlert":""},"umikaisei":{"wave":0.5,"waveFromFallback":false,"windDir":"南南西","windDeg":202.5,"windArrow":"↗️","windSpeed":5.7,"windAlert":"(面荒れ注意・オンショア)","tide":59,"tideTrend":"up"},"windy":{"wave":0.4,"wavePeriod":5.65,"windDir":"南南西","windDeg":200,"windArrow":"⬆️","windSpeed":4.46,"windAlert":""},"gfs":{"windDir":"南南西","windDeg":198,"windArrow":"⬆️","windSpeed":4.11,"windAlert":""},"tideBadge":null},{"key":"2026-07-21T16:00","hour":16,"label":"16:00","dateLabel":"7/21","isNight":false,"yahoo":{"icon":"☀️","desc":"晴れ","temp":32,"rainMm":0,"pop":83,"windDir":"南南西","windDeg":202.5,"windArrow":"↗️","windSpeed":4,"windAlert":""},"umikaisei":{"wave":0.5,"waveFromFallback":false,"windDir":"南南西","windDeg":202.5,"windArrow":"↗️","windSpeed":5.2,"windAlert":"(面荒れ注意・オンショア)","tide":63,"tideTrend":"up"},"windy":{"wave":0.42,"wavePeriod":5.5,"windDir":"南南西","windDeg":201,"windArrow":"⬆️","windSpeed":4.18,"windAlert":""},"gfs":{"windDir":"南南西","windDeg":198,"windArrow":"⬆️","windSpeed":3.98,"windAlert":""},"tideBadge":null},{"key":"2026-07-21T17:00","hour":17,"label":"17:00","dateLabel":"7/21","isNight":false,"yahoo":{"icon":"☀️","desc":"晴れ","temp":32,"rainMm":0,"pop":62,"windDir":"南南西","windDeg":202.5,"windArrow":"↗️","windSpeed":4,"windAlert":""},"umikaisei":{"wave":0.6,"waveFromFallback":false,"windDir":"南南西","windDeg":202.5,"windArrow":"↗️","windSpeed":5.7,"windAlert":"(面荒れ注意・オンショア)","tide":75,"tideTrend":"up"},"windy":{"wave":0.42,"wavePeriod":5.35,"windDir":"南南西","windDeg":199,"windArrow":"⬆️","windSpeed":3.7,"windAlert":""},"gfs":{"windDir":"南南西","windDeg":195,"windArrow":"⬆️","windSpeed":4.15,"windAlert":""},"tideBadge":null},{"key":"2026-07-21T18:00","hour":18,"label":"18:00","dateLabel":"7/21","isNight":false,"yahoo":{"icon":"☀️","desc":"晴れ","temp":30,"rainMm":0,"pop":43,"windDir":"南南西","windDeg":202.5,"windArrow":"↗️","windSpeed":3,"windAlert":""},"umikaisei":{"wave":0.6,"waveFromFallback":false,"windDir":"南南西","windDeg":202.5,"windArrow":"↗️","windSpeed":6.3,"windAlert":"(面荒れ注意・オンショア)","tide":93,"tideTrend":"up"},"windy":{"wave":0.44,"wavePeriod":5.25,"windDir":"南南西","windDeg":194,"windArrow":"⬆️","windSpeed":2.98,"windAlert":""},"gfs":{"windDir":"南","windDeg":191,"windArrow":"⬆️","windSpeed":4.28,"windAlert":""},"tideBadge":null},{"key":"2026-07-21T19:00","hour":19,"label":"19:00","dateLabel":"7/21","isNight":false,"yahoo":{"icon":"☀️","desc":"晴れ","temp":30,"rainMm":0,"pop":29,"windDir":"南南西","windDeg":202.5,"windArrow":"↗️","windSpeed":3,"windAlert":""},"umikaisei":{"wave":0.7,"waveFromFallback":false,"windDir":"南南西","windDeg":202.5,"windArrow":"↗️","windSpeed":6.8,"windAlert":"(面荒れ注意・オンショア)","tide":112,"tideTrend":"up"},"windy":{"wave":0.44,"wavePeriod":5.25,"windDir":"南","windDeg":183,"windArrow":"⬆️","windSpeed":2,"windAlert":""},"gfs":{"windDir":"南","windDeg":184,"windArrow":"⬆️","windSpeed":4.01,"windAlert":""},"tideBadge":null},{"key":"2026-07-21T20:00","hour":20,"label":"20:00","dateLabel":"7/21","isNight":false,"yahoo":{"icon":"☀️","desc":"晴れ","temp":30,"rainMm":0,"pop":17,"windDir":"南南西","windDeg":202.5,"windArrow":"↗️","windSpeed":3,"windAlert":""},"umikaisei":{"wave":0.7,"waveFromFallback":false,"windDir":"南南西","windDeg":202.5,"windArrow":"↗️","windSpeed":6.8,"windAlert":"(面荒れ注意・オンショア)","tide":129,"tideTrend":"up"},"windy":{"wave":0.44,"wavePeriod":5.3,"windDir":"南","windDeg":186,"windArrow":"⬆️","windSpeed":2.01,"windAlert":""},"gfs":{"windDir":"南","windDeg":173,"windArrow":"⬆️","windSpeed":3.32,"windAlert":""},"tideBadge":null},{"key":"2026-07-21T21:00","hour":21,"label":"21:00","dateLabel":"7/21","isNight":false,"yahoo":{"icon":"☀️","desc":"晴れ","temp":28,"rainMm":0,"pop":8,"windDir":"南南西","windDeg":202.5,"windArrow":"↗️","windSpeed":2,"windAlert":""},"umikaisei":{"wave":0.8,"waveFromFallback":false,"windDir":"南南西","windDeg":202.5,"windArrow":"↗️","windSpeed":7.3,"windAlert":"(面荒れ注意・オンショア)","tide":138,"tideTrend":"up"},"windy":{"wave":0.44,"wavePeriod":5.4,"windDir":"南","windDeg":185,"windArrow":"⬆️","windSpeed":1.2,"windAlert":""},"gfs":{"windDir":"南","windDeg":169,"windArrow":"⬆️","windSpeed":2.55,"windAlert":""},"tideBadge":"🛑 満潮間近"},{"key":"2026-07-21T22:00","hour":22,"label":"22:00","dateLabel":"7/21","isNight":false,"yahoo":{"icon":"☀️","desc":"晴れ","temp":28,"rainMm":0,"pop":3,"windDir":"南南西","windDeg":202.5,"windArrow":"↗️","windSpeed":2,"windAlert":""},"umikaisei":{"wave":0.8,"waveFromFallback":false,"windDir":"南南西","windDeg":202.5,"windArrow":"↗️","windSpeed":7.6,"windAlert":"(面荒れ注意・オンショア)","tide":139,"tideTrend":"down"},"windy":{"wave":0.44,"wavePeriod":5.5,"windDir":"南東","windDeg":146,"windArrow":"↖️","windSpeed":0.36,"windAlert":""},"gfs":{"windDir":"南","windDeg":188,"windArrow":"⬆️","windSpeed":2.12,"windAlert":""},"tideBadge":null},{"key":"2026-07-21T23:00","hour":23,"label":"23:00","dateLabel":"7/21","isNight":false,"yahoo":{"icon":"☀️","desc":"晴れ","temp":28,"rainMm":0,"pop":1,"windDir":"南南西","windDeg":202.5,"windArrow":"↗️","windSpeed":2,"windAlert":""},"umikaisei":{"wave":0.8,"waveFromFallback":false,"windDir":"南南西","windDeg":202.5,"windArrow":"↗️","windSpeed":7.1,"windAlert":"(面荒れ注意・オンショア)","tide":130,"tideTrend":"down"},"windy":{"wave":0.42,"wavePeriod":5.65,"windDir":"南南東","windDeg":162,"windArrow":"⬆️","windSpeed":0.63,"windAlert":""},"gfs":{"windDir":"南南西","windDeg":196,"windArrow":"⬆️","windSpeed":2.18,"windAlert":""},"tideBadge":null},{"key":"2026-07-22T00:00","hour":0,"label":"00:00","dateLabel":"7/22","isNight":true,"yahoo":{"icon":"","desc":"","temp":null,"rainMm":null,"pop":0,"windDir":"--","windDeg":null,"windArrow":"","windSpeed":null,"windAlert":""},"umikaisei":{"wave":0.7,"waveFromFallback":false,"windDir":"南西","windDeg":225,"windArrow":"↗️","windSpeed":6.4,"windAlert":"(面荒れ注意・オンショア)","tide":114,"tideTrend":"down"},"windy":{"wave":0.42,"wavePeriod":5.75,"windDir":"南","windDeg":180,"windArrow":"⬆️","windSpeed":0.7,"windAlert":""},"gfs":{"windDir":"南南西","windDeg":198,"windArrow":"⬆️","windSpeed":1.9,"windAlert":""},"tideBadge":null},{"key":"2026-07-22T01:00","hour":1,"label":"01:00","dateLabel":"7/22","isNight":true,"yahoo":{"icon":"","desc":"","temp":null,"rainMm":null,"pop":0,"windDir":"--","windDeg":null,"windArrow":"","windSpeed":null,"windAlert":""},"umikaisei":{"wave":0.7,"waveFromFallback":false,"windDir":"南西","windDeg":225,"windArrow":"↗️","windSpeed":4.7,"windAlert":"","tide":95,"tideTrend":"down"},"windy":{"wave":0.42,"wavePeriod":5.85,"windDir":"南","windDeg":180,"windArrow":"⬆️","windSpeed":0.7,"windAlert":""},"gfs":{"windDir":"南南西","windDeg":207,"windArrow":"↗️","windSpeed":1.12,"windAlert":""},"tideBadge":null},{"key":"2026-07-22T02:00","hour":2,"label":"02:00","dateLabel":"7/22","isNight":true,"yahoo":{"icon":"","desc":"","temp":null,"rainMm":null,"pop":0,"windDir":"--","windDeg":null,"windArrow":"","windSpeed":null,"windAlert":""},"umikaisei":{"wave":0.7,"waveFromFallback":false,"windDir":"西南西","windDeg":247.5,"windArrow":"➡️","windSpeed":3.7,"windAlert":"","tide":77,"tideTrend":"down"},"windy":{"wave":0.4,"wavePeriod":5.95,"windDir":"南","windDeg":188,"windArrow":"⬆️","windSpeed":0.71,"windAlert":""},"gfs":{"windDir":"南西","windDeg":217,"windArrow":"↗️","windSpeed":0.5,"windAlert":""},"tideBadge":"🟢 干潮間近"},{"key":"2026-07-22T03:00","hour":3,"label":"03:00","dateLabel":"7/22","isNight":true,"yahoo":{"icon":"","desc":"","temp":null,"rainMm":null,"pop":0,"windDir":"--","windDeg":null,"windArrow":"","windSpeed":null,"windAlert":""},"umikaisei":{"wave":0.7,"waveFromFallback":false,"windDir":"西","windDeg":270,"windArrow":"➡️","windSpeed":3.4,"windAlert":"","tide":64,"tideTrend":"down"},"windy":{"wave":0.4,"wavePeriod":6.05,"windDir":"南","windDeg":187,"windArrow":"⬆️","windSpeed":0.81,"windAlert":""},"gfs":{"windDir":"西北西","windDeg":301,"windArrow":"↘️","windSpeed":0.58,"windAlert":""},"tideBadge":null},{"key":"2026-07-22T04:00","hour":4,"label":"04:00","dateLabel":"7/22","isNight":true,"yahoo":{"icon":"","desc":"","temp":null,"rainMm":null,"pop":0,"windDir":"--","windDeg":null,"windArrow":"","windSpeed":null,"windAlert":""},"umikaisei":{"wave":0.6,"waveFromFallback":false,"windDir":"西北西","windDeg":292.5,"windArrow":"↘️","windSpeed":2.6,"windAlert":"","tide":58,"tideTrend":"up"},"windy":{"wave":0.4,"wavePeriod":6.05,"windDir":"南","windDeg":187,"windArrow":"⬆️","windSpeed":0.81,"windAlert":""},"gfs":{"windDir":"北北西","windDeg":335,"windArrow":"↘️","windSpeed":1.43,"windAlert":""},"tideBadge":null},{"key":"2026-07-22T05:00","hour":5,"label":"05:00","dateLabel":"7/22","isNight":false,"yahoo":{"icon":"","desc":"","temp":null,"rainMm":null,"pop":0,"windDir":"--","windDeg":null,"windArrow":"","windSpeed":null,"windAlert":""},"umikaisei":{"wave":0.6,"waveFromFallback":false,"windDir":"北西","windDeg":315,"windArrow":"↘️","windSpeed":2,"windAlert":"","tide":61,"tideTrend":"up"},"windy":{"wave":0.4,"wavePeriod":6.05,"windDir":"南","windDeg":188,"windArrow":"⬆️","windSpeed":0.71,"windAlert":""},"gfs":{"windDir":"北","windDeg":2,"windArrow":"⬇️","windSpeed":2.4,"windAlert":""},"tideBadge":null},{"key":"2026-07-22T06:00","hour":6,"label":"06:00","dateLabel":"7/22","isNight":false,"yahoo":{"icon":"","desc":"","temp":null,"rainMm":null,"pop":0,"windDir":"--","windDeg":null,"windArrow":"","windSpeed":null,"windAlert":""},"umikaisei":{"wave":0.5,"waveFromFallback":false,"windDir":"北","windDeg":0,"windArrow":"⬇️","windSpeed":2.2,"windAlert":"","tide":72,"tideTrend":"up"},"windy":{"wave":0.4,"wavePeriod":6.05,"windDir":"南","windDeg":180,"windArrow":"⬆️","windSpeed":0.4,"windAlert":""},"gfs":{"windDir":"北北東","windDeg":25,"windArrow":"↙️","windSpeed":2.64,"windAlert":""},"tideBadge":null},{"key":"2026-07-22T07:00","hour":7,"label":"07:00","dateLabel":"7/22","isNight":false,"yahoo":{"icon":"","desc":"","temp":null,"rainMm":null,"pop":0,"windDir":"--","windDeg":null,"windArrow":"","windSpeed":null,"windAlert":""},"umikaisei":{"wave":0.5,"waveFromFallback":false,"windDir":"北北東","windDeg":22.5,"windArrow":"↙️","windSpeed":2.9,"windAlert":"","tide":86,"tideTrend":"up"},"windy":{"wave":0.4,"wavePeriod":6.05,"windDir":"南","windDeg":189,"windArrow":"⬆️","windSpeed":0.61,"windAlert":""},"gfs":{"windDir":"北東","windDeg":47,"windArrow":"↙️","windSpeed":2.33,"windAlert":""},"tideBadge":null},{"key":"2026-07-22T08:00","hour":8,"label":"08:00","dateLabel":"7/22","isNight":false,"yahoo":{"icon":"","desc":"","temp":null,"rainMm":null,"pop":0,"windDir":"--","windDeg":null,"windArrow":"","windSpeed":null,"windAlert":""},"umikaisei":{"wave":0.5,"waveFromFallback":false,"windDir":"北東","windDeg":45,"windArrow":"↙️","windSpeed":4.1,"windAlert":"","tide":101,"tideTrend":"up"},"windy":{"wave":0.38,"wavePeriod":6.1,"windDir":"南南西","windDeg":195,"windArrow":"⬆️","windSpeed":1.55,"windAlert":""},"gfs":{"windDir":"東北東","windDeg":63,"windArrow":"↙️","windSpeed":2.01,"windAlert":""},"tideBadge":"🛑 満潮間近"},{"key":"2026-07-22T09:00","hour":9,"label":"09:00","dateLabel":"7/22","isNight":false,"yahoo":{"icon":"","desc":"","temp":null,"rainMm":null,"pop":0,"windDir":"--","windDeg":null,"windArrow":"","windSpeed":null,"windAlert":""},"umikaisei":{"wave":0.4,"waveFromFallback":false,"windDir":"東北東","windDeg":67.5,"windArrow":"⬅️","windSpeed":3.8,"windAlert":"","tide":112,"tideTrend":"up"},"windy":{"wave":0.38,"wavePeriod":6.1,"windDir":"南南西","windDeg":207,"windArrow":"↗️","windSpeed":2.01,"windAlert":""},"gfs":{"windDir":"東","windDeg":93,"windArrow":"⬅️","windSpeed":1.8,"windAlert":""},"tideBadge":null},{"key":"2026-07-22T10:00","hour":10,"label":"10:00","dateLabel":"7/22","isNight":false,"yahoo":{"icon":"","desc":"","temp":null,"rainMm":null,"pop":6,"windDir":"--","windDeg":null,"windArrow":"","windSpeed":null,"windAlert":""},"umikaisei":{"wave":0.4,"waveFromFallback":false,"windDir":"東北東","windDeg":67.5,"windArrow":"⬅️","windSpeed":3,"windAlert":"","tide":118,"tideTrend":"down"},"windy":{"wave":0.38,"wavePeriod":6.1,"windDir":"南南西","windDeg":208,"windArrow":"↗️","windSpeed":2.37,"windAlert":""},"gfs":{"windDir":"南東","windDeg":131,"windArrow":"↖️","windSpeed":1.98,"windAlert":""},"tideBadge":null},{"key":"2026-07-22T11:00","hour":11,"label":"11:00","dateLabel":"7/22","isNight":false,"yahoo":{"icon":"","desc":"","temp":null,"rainMm":null,"pop":14,"windDir":"--","windDeg":null,"windArrow":"","windSpeed":null,"windAlert":""},"umikaisei":{"wave":0.4,"waveFromFallback":false,"windDir":"東","windDeg":90,"windArrow":"⬅️","windSpeed":1.3,"windAlert":"","tide":116,"tideTrend":"down"},"windy":{"wave":0.38,"wavePeriod":6.05,"windDir":"南南西","windDeg":201,"windArrow":"⬆️","windSpeed":3.01,"windAlert":""},"gfs":{"windDir":"南","windDeg":169,"windArrow":"⬆️","windSpeed":2.65,"windAlert":""},"tideBadge":null},{"key":"2026-07-22T12:00","hour":12,"label":"12:00","dateLabel":"7/22","isNight":false,"yahoo":{"icon":"","desc":"","temp":null,"rainMm":null,"pop":27,"windDir":"--","windDeg":null,"windArrow":"","windSpeed":null,"windAlert":""},"umikaisei":{"wave":0.4,"waveFromFallback":false,"windDir":"南西","windDeg":225,"windArrow":"↗️","windSpeed":4.3,"windAlert":"","tide":108,"tideTrend":"down"},"windy":{"wave":0.38,"wavePeriod":6,"windDir":"南南西","windDeg":199,"windArrow":"⬆️","windSpeed":3.38,"windAlert":""},"gfs":{"windDir":"南","windDeg":188,"windArrow":"⬆️","windSpeed":3.63,"windAlert":""},"tideBadge":null},{"key":"2026-07-22T13:00","hour":13,"label":"13:00","dateLabel":"7/22","isNight":false,"yahoo":{"icon":"","desc":"","temp":null,"rainMm":null,"pop":49,"windDir":"--","windDeg":null,"windArrow":"","windSpeed":null,"windAlert":""},"umikaisei":{"wave":0.4,"waveFromFallback":false,"windDir":"南西","windDeg":225,"windArrow":"↗️","windSpeed":5.2,"windAlert":"(面荒れ注意・オンショア)","tide":97,"tideTrend":"down"},"windy":{"wave":0.4,"wavePeriod":5.85,"windDir":"南南西","windDeg":195,"windArrow":"⬆️","windSpeed":3.93,"windAlert":""},"gfs":{"windDir":"南","windDeg":185,"windArrow":"⬆️","windSpeed":4.32,"windAlert":""},"tideBadge":null},{"key":"2026-07-22T14:00","hour":14,"label":"14:00","dateLabel":"7/22","isNight":false,"yahoo":{"icon":"","desc":"","temp":null,"rainMm":null,"pop":76,"windDir":"--","windDeg":null,"windArrow":"","windSpeed":null,"windAlert":""},"umikaisei":{"wave":0.4,"waveFromFallback":false,"windDir":"南西","windDeg":225,"windArrow":"↗️","windSpeed":5.1,"windAlert":"(面荒れ注意・オンショア)","tide":85,"tideTrend":"down"},"windy":{"wave":0.4,"wavePeriod":5.6,"windDir":"南南西","windDeg":196,"windArrow":"⬆️","windSpeed":4.05,"windAlert":""},"gfs":{"windDir":"南南西","windDeg":192,"windArrow":"⬆️","windSpeed":5,"windAlert":"(面荒れ注意・オンショア)"},"tideBadge":"🟢 干潮間近"},{"key":"2026-07-22T15:00","hour":15,"label":"15:00","dateLabel":"7/22","isNight":false,"yahoo":{"icon":"","desc":"","temp":null,"rainMm":null,"pop":90,"windDir":"--","windDeg":null,"windArrow":"","windSpeed":null,"windAlert":""},"umikaisei":{"wave":0.4,"waveFromFallback":false,"windDir":"南南西","windDeg":202.5,"windArrow":"↗️","windSpeed":5.3,"windAlert":"(面荒れ注意・オンショア)","tide":77,"tideTrend":"down"},"windy":{"wave":0.42,"wavePeriod":5.45,"windDir":"南南西","windDeg":196,"windArrow":"⬆️","windSpeed":3.96,"windAlert":""},"gfs":{"windDir":"南南西","windDeg":194,"windArrow":"⬆️","windSpeed":4.54,"windAlert":""},"tideBadge":null},{"key":"2026-07-22T16:00","hour":16,"label":"16:00","dateLabel":"7/22","isNight":false,"yahoo":{"icon":"","desc":"","temp":null,"rainMm":null,"pop":82,"windDir":"--","windDeg":null,"windArrow":"","windSpeed":null,"windAlert":""},"umikaisei":{"wave":0.42,"waveFromFallback":true,"windDir":"--","windDeg":194,"windArrow":"⬆️","windSpeed":3.81,"windAlert":"","tide":76,"tideTrend":"up"},"windy":{"wave":0.42,"wavePeriod":5.4,"windDir":"南南西","windDeg":194,"windArrow":"⬆️","windSpeed":3.81,"windAlert":""},"gfs":{"windDir":"南","windDeg":187,"windArrow":"⬆️","windSpeed":4.84,"windAlert":""},"tideBadge":null},{"key":"2026-07-22T17:00","hour":17,"label":"17:00","dateLabel":"7/22","isNight":false,"yahoo":{"icon":"","desc":"","temp":null,"rainMm":null,"pop":61,"windDir":"--","windDeg":null,"windArrow":"","windSpeed":null,"windAlert":""},"umikaisei":{"wave":0.44,"waveFromFallback":true,"windDir":"--","windDeg":189,"windArrow":"⬆️","windSpeed":3.65,"windAlert":"","tide":81,"tideTrend":"up"},"windy":{"wave":0.44,"wavePeriod":5.4,"windDir":"南","windDeg":189,"windArrow":"⬆️","windSpeed":3.65,"windAlert":""},"gfs":{"windDir":"南南西","windDeg":194,"windArrow":"⬆️","windSpeed":4.63,"windAlert":""},"tideBadge":null},{"key":"2026-07-22T18:00","hour":18,"label":"18:00","dateLabel":"7/22","isNight":false,"yahoo":{"icon":"","desc":"","temp":null,"rainMm":null,"pop":41,"windDir":"--","windDeg":null,"windArrow":"","windSpeed":null,"windAlert":""},"umikaisei":{"wave":0.44,"waveFromFallback":true,"windDir":"--","windDeg":188,"windArrow":"⬆️","windSpeed":2.83,"windAlert":"","tide":92,"tideTrend":"up"},"windy":{"wave":0.44,"wavePeriod":5.4,"windDir":"南","windDeg":188,"windArrow":"⬆️","windSpeed":2.83,"windAlert":""},"gfs":{"windDir":"南南西","windDeg":194,"windArrow":"⬆️","windSpeed":3.81,"windAlert":""},"tideBadge":null},{"key":"2026-07-22T19:00","hour":19,"label":"19:00","dateLabel":"7/22","isNight":false,"yahoo":{"icon":"","desc":"","temp":null,"rainMm":null,"pop":26,"windDir":"--","windDeg":null,"windArrow":"","windSpeed":null,"windAlert":""},"umikaisei":{"wave":0.44,"waveFromFallback":true,"windDir":"--","windDeg":177,"windArrow":"⬆️","windSpeed":2,"windAlert":"","tide":107,"tideTrend":"up"},"windy":{"wave":0.44,"wavePeriod":5.4,"windDir":"南","windDeg":177,"windArrow":"⬆️","windSpeed":2,"windAlert":""},"gfs":{"windDir":"南","windDeg":175,"windArrow":"⬆️","windSpeed":3.31,"windAlert":""},"tideBadge":null},{"key":"2026-07-22T20:00","hour":20,"label":"20:00","dateLabel":"7/22","isNight":false,"yahoo":{"icon":"","desc":"","temp":null,"rainMm":null,"pop":12,"windDir":"--","windDeg":null,"windArrow":"","windSpeed":null,"windAlert":""},"umikaisei":{"wave":0.46,"waveFromFallback":true,"windDir":"--","windDeg":165,"windArrow":"⬆️","windSpeed":1.55,"windAlert":"","tide":123,"tideTrend":"up"},"windy":{"wave":0.46,"wavePeriod":5.4,"windDir":"南南東","windDeg":165,"windArrow":"⬆️","windSpeed":1.55,"windAlert":""},"gfs":{"windDir":"南南東","windDeg":153,"windArrow":"↖️","windSpeed":3.8,"windAlert":""},"tideBadge":null},{"key":"2026-07-22T21:00","hour":21,"label":"21:00","dateLabel":"7/22","isNight":false,"yahoo":{"icon":"","desc":"","temp":null,"rainMm":null,"pop":2,"windDir":"--","windDeg":null,"windArrow":"","windSpeed":null,"windAlert":""},"umikaisei":{"wave":0.46,"waveFromFallback":true,"windDir":"--","windDeg":160,"windArrow":"⬆️","windSpeed":1.49,"windAlert":"","tide":134,"tideTrend":"up"},"windy":{"wave":0.46,"wavePeriod":5.4,"windDir":"南南東","windDeg":160,"windArrow":"⬆️","windSpeed":1.49,"windAlert":""},"gfs":{"windDir":"南","windDeg":172,"windArrow":"⬆️","windSpeed":2.22,"windAlert":""},"tideBadge":"🛑 満潮間近"},{"key":"2026-07-22T22:00","hour":22,"label":"22:00","dateLabel":"7/22","isNight":false,"yahoo":{"icon":"","desc":"","temp":null,"rainMm":null,"pop":0,"windDir":"--","windDeg":null,"windArrow":"","windSpeed":null,"windAlert":""},"umikaisei":{"wave":0.46,"waveFromFallback":true,"windDir":"--","windDeg":165,"windArrow":"⬆️","windSpeed":1.14,"windAlert":"","tide":139,"tideTrend":"down"},"windy":{"wave":0.46,"wavePeriod":5.4,"windDir":"南南東","windDeg":165,"windArrow":"⬆️","windSpeed":1.14,"windAlert":""},"gfs":{"windDir":"東南東","windDeg":112,"windArrow":"⬅️","windSpeed":1.08,"windAlert":""},"tideBadge":null},{"key":"2026-07-22T23:00","hour":23,"label":"23:00","dateLabel":"7/22","isNight":false,"yahoo":{"icon":"","desc":"","temp":null,"rainMm":null,"pop":1,"windDir":"--","windDeg":null,"windArrow":"","windSpeed":null,"windAlert":""},"umikaisei":{"wave":0.48,"waveFromFallback":true,"windDir":"--","windDeg":174,"windArrow":"⬆️","windSpeed":0.91,"windAlert":"","tide":136,"tideTrend":"down"},"windy":{"wave":0.48,"wavePeriod":5.4,"windDir":"南","windDeg":174,"windArrow":"⬆️","windSpeed":0.91,"windAlert":""},"gfs":{"windDir":"東南東","windDeg":122,"windArrow":"↖️","windSpeed":1.89,"windAlert":""},"tideBadge":null},{"key":"2026-07-23T00:00","hour":0,"label":"00:00","dateLabel":"7/23","isNight":true,"yahoo":{"icon":"","desc":"","temp":null,"rainMm":null,"pop":2,"windDir":"--","windDeg":null,"windArrow":"","windSpeed":null,"windAlert":""},"umikaisei":{"wave":0.48,"waveFromFallback":true,"windDir":"--","windDeg":180,"windArrow":"⬆️","windSpeed":0.4,"windAlert":"","tide":124,"tideTrend":"down"},"windy":{"wave":0.48,"wavePeriod":5.45,"windDir":"南","windDeg":180,"windArrow":"⬆️","windSpeed":0.4,"windAlert":""},"gfs":{"windDir":"南東","windDeg":129,"windArrow":"↖️","windSpeed":1.42,"windAlert":""},"tideBadge":null},{"key":"2026-07-23T01:00","hour":1,"label":"01:00","dateLabel":"7/23","isNight":true,"yahoo":{"icon":"","desc":"","temp":null,"rainMm":null,"pop":2,"windDir":"--","windDeg":null,"windArrow":"","windSpeed":null,"windAlert":""},"umikaisei":{"wave":0.48,"waveFromFallback":true,"windDir":"--","windDeg":135,"windArrow":"↖️","windSpeed":0.57,"windAlert":"","tide":107,"tideTrend":"down"},"windy":{"wave":0.48,"wavePeriod":5.5,"windDir":"南東","windDeg":135,"windArrow":"↖️","windSpeed":0.57,"windAlert":""},"gfs":{"windDir":"東北東","windDeg":75,"windArrow":"⬅️","windSpeed":1.96,"windAlert":""},"tideBadge":null},{"key":"2026-07-23T02:00","hour":2,"label":"02:00","dateLabel":"7/23","isNight":true,"yahoo":{"icon":"","desc":"","temp":null,"rainMm":null,"pop":2,"windDir":"--","windDeg":null,"windArrow":"","windSpeed":null,"windAlert":""},"umikaisei":{"wave":0.46,"waveFromFallback":true,"windDir":"--","windDeg":166,"windArrow":"⬆️","windSpeed":0.41,"windAlert":"","tide":88,"tideTrend":"down"},"windy":{"wave":0.46,"wavePeriod":5.6,"windDir":"南南東","windDeg":166,"windArrow":"⬆️","windSpeed":0.41,"windAlert":""},"gfs":{"windDir":"東北東","windDeg":69,"windArrow":"⬅️","windSpeed":1.93,"windAlert":""},"tideBadge":"🟢 干潮間近"},{"key":"2026-07-23T03:00","hour":3,"label":"03:00","dateLabel":"7/23","isNight":true,"yahoo":{"icon":"","desc":"","temp":null,"rainMm":null,"pop":2,"windDir":"--","windDeg":null,"windArrow":"","windSpeed":null,"windAlert":""},"umikaisei":{"wave":0.46,"waveFromFallback":true,"windDir":"--","windDeg":180,"windArrow":"⬆️","windSpeed":0.5,"windAlert":"","tide":70,"tideTrend":"down"},"windy":{"wave":0.46,"wavePeriod":5.7,"windDir":"南","windDeg":180,"windArrow":"⬆️","windSpeed":0.5,"windAlert":""},"gfs":{"windDir":"北東","windDeg":43,"windArrow":"↙️","windSpeed":1.91,"windAlert":""},"tideBadge":null}],"sources":{"yahoo":true,"umikaisei":true,"umikaiseiTide":true,"openMeteo":true},"debug":{"hours":85,"tideHighs":2}},"zushi":{"generatedAt":"2026-07-19T18:10:31.995Z","tide":{"tideName":"小潮","moonAge":5,"highs":[{"time":"08:05","level":136},{"time":"21:04","level":141}],"lows":[{"time":"02:24","level":71},{"time":"14:31","level":43}],"advice":"本日は小潮。満潮08:05・干潮02:24を目安に行動を。"},"timeline":[{"key":"2026-07-20T03:00","hour":3,"label":"03:00","dateLabel":"7/20","isNight":true,"yahoo":{"icon":"☀️","desc":"晴れ","temp":26,"rainMm":0,"pop":0,"windDir":"南南西","windDeg":202.5,"windArrow":"↗️","windSpeed":2,"windAlert":""},"umikaisei":{"wave":0.5,"waveFromFallback":false,"windDir":"南南西","windDeg":202.5,"windArrow":"↗️","windSpeed":6.2,"windAlert":"(面荒れ注意・オンショア)","tide":73,"tideTrend":"up"},"windy":{"wave":0.46,"wavePeriod":5.85,"windDir":"南南西","windDeg":192,"windArrow":"⬆️","windSpeed":1.94,"windAlert":""},"gfs":{"windDir":"南南西","windDeg":195,"windArrow":"⬆️","windSpeed":2.28,"windAlert":""},"tideBadge":null},{"key":"2026-07-20T04:00","hour":4,"label":"04:00","dateLabel":"7/20","isNight":true,"yahoo":{"icon":"☀️","desc":"晴れ","temp":26,"rainMm":0,"pop":0,"windDir":"南南西","windDeg":202.5,"windArrow":"↗️","windSpeed":2,"windAlert":""},"umikaisei":{"wave":0.5,"waveFromFallback":false,"windDir":"南南西","windDeg":202.5,"windArrow":"↗️","windSpeed":5.6,"windAlert":"(面荒れ注意・オンショア)","tide":83,"tideTrend":"up"},"windy":{"wave":0.44,"wavePeriod":5.95,"windDir":"南","windDeg":191,"windArrow":"⬆️","windSpeed":1.63,"windAlert":""},"gfs":{"windDir":"南南西","windDeg":199,"windArrow":"⬆️","windSpeed":2.12,"windAlert":""},"tideBadge":null},{"key":"2026-07-20T05:00","hour":5,"label":"05:00","dateLabel":"7/20","isNight":false,"yahoo":{"icon":"☀️","desc":"晴れ","temp":26,"rainMm":0,"pop":0,"windDir":"南南西","windDeg":202.5,"windArrow":"↗️","windSpeed":2,"windAlert":""},"umikaisei":{"wave":0.5,"waveFromFallback":false,"windDir":"南西","windDeg":225,"windArrow":"↗️","windSpeed":4.6,"windAlert":"","tide":99,"tideTrend":"up"},"windy":{"wave":0.44,"wavePeriod":6.05,"windDir":"南","windDeg":184,"windArrow":"⬆️","windSpeed":1.4,"windAlert":""},"gfs":{"windDir":"南南西","windDeg":198,"windArrow":"⬆️","windSpeed":1.99,"windAlert":""},"tideBadge":null},{"key":"2026-07-20T06:00","hour":6,"label":"06:00","dateLabel":"7/20","isNight":false,"yahoo":{"icon":"☀️","desc":"晴れ","temp":27,"rainMm":0,"pop":0,"windDir":"南南西","windDeg":202.5,"windArrow":"↗️","windSpeed":1,"windAlert":""},"umikaisei":{"wave":0.5,"waveFromFallback":false,"windDir":"南西","windDeg":225,"windArrow":"↗️","windSpeed":3.2,"windAlert":"","tide":116,"tideTrend":"up"},"windy":{"wave":0.42,"wavePeriod":6.1,"windDir":"南","windDeg":180,"windArrow":"⬆️","windSpeed":1.3,"windAlert":""},"gfs":{"windDir":"南南西","windDeg":197,"windArrow":"⬆️","windSpeed":1.68,"windAlert":""},"tideBadge":null},{"key":"2026-07-20T07:00","hour":7,"label":"07:00","dateLabel":"7/20","isNight":false,"yahoo":{"icon":"☀️","desc":"晴れ","temp":27,"rainMm":0,"pop":0,"windDir":"南南西","windDeg":202.5,"windArrow":"↗️","windSpeed":1,"windAlert":""},"umikaisei":{"wave":0.5,"waveFromFallback":false,"windDir":"西南西","windDeg":247.5,"windArrow":"➡️","windSpeed":1.6,"windAlert":"","tide":130,"tideTrend":"up"},"windy":{"wave":0.42,"wavePeriod":6.15,"windDir":"南","windDeg":187,"windArrow":"⬆️","windSpeed":1.71,"windAlert":""},"gfs":{"windDir":"南南西","windDeg":195,"windArrow":"⬆️","windSpeed":1.14,"windAlert":""},"tideBadge":null},{"key":"2026-07-20T08:00","hour":8,"label":"08:00","dateLabel":"7/20","isNight":false,"yahoo":{"icon":"☀️","desc":"晴れ","temp":27,"rainMm":0,"pop":0,"windDir":"南南西","windDeg":202.5,"windArrow":"↗️","windSpeed":1,"windAlert":""},"umikaisei":{"wave":0.5,"waveFromFallback":false,"windDir":"南西","windDeg":225,"windArrow":"↗️","windSpeed":1.3,"windAlert":"","tide":136,"tideTrend":"down"},"windy":{"wave":0.4,"wavePeriod":6.2,"windDir":"南南西","windDeg":195,"windArrow":"⬆️","windSpeed":1.96,"windAlert":""},"gfs":{"windDir":"南南東","windDeg":162,"windArrow":"⬆️","windSpeed":1.26,"windAlert":""},"tideBadge":"🛑 満潮間近"},{"key":"2026-07-20T09:00","hour":9,"label":"09:00","dateLabel":"7/20","isNight":false,"yahoo":{"icon":"☀️","desc":"晴れ","temp":31,"rainMm":0,"pop":0,"windDir":"南南西","windDeg":202.5,"windArrow":"↗️","windSpeed":2,"windAlert":""},"umikaisei":{"wave":0.4,"waveFromFallback":false,"windDir":"南南西","windDeg":202.5,"windArrow":"↗️","windSpeed":2,"windAlert":"","tide":131,"tideTrend":"down"},"windy":{"wave":0.4,"wavePeriod":6.25,"windDir":"南南西","windDeg":197,"windArrow":"⬆️","windSpeed":2.09,"windAlert":""},"gfs":{"windDir":"南","windDeg":172,"windArrow":"⬆️","windSpeed":2.12,"windAlert":""},"tideBadge":null},{"key":"2026-07-20T10:00","hour":10,"label":"10:00","dateLabel":"7/20","isNight":false,"yahoo":{"icon":"☀️","desc":"晴れ","temp":31,"rainMm":0,"pop":0,"windDir":"南南西","windDeg":202.5,"windArrow":"↗️","windSpeed":2,"windAlert":""},"umikaisei":{"wave":0.4,"waveFromFallback":false,"windDir":"南南西","windDeg":202.5,"windArrow":"↗️","windSpeed":3.5,"windAlert":"","tide":118,"tideTrend":"down"},"windy":{"wave":0.4,"wavePeriod":6.3,"windDir":"南南西","windDeg":195,"windArrow":"⬆️","windSpeed":2.38,"windAlert":""},"gfs":{"windDir":"南","windDeg":180,"windArrow":"⬆️","windSpeed":2.6,"windAlert":""},"tideBadge":null},{"key":"2026-07-20T11:00","hour":11,"label":"11:00","dateLabel":"7/20","isNight":false,"yahoo":{"icon":"☀️","desc":"晴れ","temp":31,"rainMm":0,"pop":0,"windDir":"南南西","windDeg":202.5,"windArrow":"↗️","windSpeed":2,"windAlert":""},"umikaisei":{"wave":0.4,"waveFromFallback":false,"windDir":"南南西","windDeg":202.5,"windArrow":"↗️","windSpeed":4.7,"windAlert":"","tide":97,"tideTrend":"down"},"windy":{"wave":0.4,"wavePeriod":6.35,"windDir":"南南西","windDeg":194,"windArrow":"⬆️","windSpeed":2.89,"windAlert":""},"gfs":{"windDir":"南","windDeg":182,"windArrow":"⬆️","windSpeed":3.3,"windAlert":""},"tideBadge":null},{"key":"2026-07-20T12:00","hour":12,"label":"12:00","dateLabel":"7/20","isNight":false,"yahoo":{"icon":"☀️","desc":"晴れ","temp":33,"rainMm":0,"pop":0,"windDir":"南南西","windDeg":202.5,"windArrow":"↗️","windSpeed":3,"windAlert":""},"umikaisei":{"wave":0.4,"waveFromFallback":false,"windDir":"南南西","windDeg":202.5,"windArrow":"↗️","windSpeed":6.1,"windAlert":"(面荒れ注意・オンショア)","tide":75,"tideTrend":"down"},"windy":{"wave":0.4,"wavePeriod":6.3,"windDir":"南南西","windDeg":192,"windArrow":"⬆️","windSpeed":3.37,"windAlert":""},"gfs":{"windDir":"南","windDeg":186,"windArrow":"⬆️","windSpeed":4.02,"windAlert":""},"tideBadge":null},{"key":"2026-07-20T13:00","hour":13,"label":"13:00","dateLabel":"7/20","isNight":false,"yahoo":{"icon":"☀️","desc":"晴れ","temp":33,"rainMm":0,"pop":7,"windDir":"南南西","windDeg":202.5,"windArrow":"↗️","windSpeed":3,"windAlert":""},"umikaisei":{"wave":0.5,"waveFromFallback":false,"windDir":"南南西","windDeg":202.5,"windArrow":"↗️","windSpeed":6.6,"windAlert":"(面荒れ注意・オンショア)","tide":56,"tideTrend":"down"},"windy":{"wave":0.4,"wavePeriod":6.1,"windDir":"南南西","windDeg":192,"windArrow":"⬆️","windSpeed":3.88,"windAlert":""},"gfs":{"windDir":"南","windDeg":188,"windArrow":"⬆️","windSpeed":4.44,"windAlert":""},"tideBadge":null},{"key":"2026-07-20T14:00","hour":14,"label":"14:00","dateLabel":"7/20","isNight":false,"yahoo":{"icon":"☀️","desc":"晴れ","temp":33,"rainMm":0,"pop":16,"windDir":"南南西","windDeg":202.5,"windArrow":"↗️","windSpeed":3,"windAlert":""},"umikaisei":{"wave":0.5,"waveFromFallback":false,"windDir":"南南西","windDeg":202.5,"windArrow":"↗️","windSpeed":6.9,"windAlert":"(面荒れ注意・オンショア)","tide":45,"tideTrend":null},"windy":{"wave":0.42,"wavePeriod":5.85,"windDir":"南南西","windDeg":196,"windArrow":"⬆️","windSpeed":4.37,"windAlert":""},"gfs":{"windDir":"南","windDeg":189,"windArrow":"⬆️","windSpeed":4.65,"windAlert":""},"tideBadge":"🟢 干潮間近"},{"key":"2026-07-20T15:00","hour":15,"label":"15:00","dateLabel":"7/20","isNight":false,"yahoo":{"icon":"☀️","desc":"晴れ","temp":33,"rainMm":0,"pop":20,"windDir":"南","windDeg":180,"windArrow":"⬆️","windSpeed":3,"windAlert":""},"umikaisei":{"wave":0.6,"waveFromFallback":false,"windDir":"南南西","windDeg":202.5,"windArrow":"↗️","windSpeed":6.8,"windAlert":"(面荒れ注意・オンショア)","tide":45,"tideTrend":"up"},"windy":{"wave":0.42,"wavePeriod":5.6,"windDir":"南南西","windDeg":201,"windArrow":"⬆️","windSpeed":4.49,"windAlert":""},"gfs":{"windDir":"南南西","windDeg":195,"windArrow":"⬆️","windSpeed":4.75,"windAlert":""},"tideBadge":null},{"key":"2026-07-20T16:00","hour":16,"label":"16:00","dateLabel":"7/20","isNight":false,"yahoo":{"icon":"☀️","desc":"晴れ","temp":33,"rainMm":0,"pop":16,"windDir":"南","windDeg":180,"windArrow":"⬆️","windSpeed":3,"windAlert":""},"umikaisei":{"wave":0.6,"waveFromFallback":false,"windDir":"南南西","windDeg":202.5,"windArrow":"↗️","windSpeed":7.1,"windAlert":"(面荒れ注意・オンショア)","tide":55,"tideTrend":"up"},"windy":{"wave":0.44,"wavePeriod":5.35,"windDir":"南南西","windDeg":196,"windArrow":"⬆️","windSpeed":4.37,"windAlert":""},"gfs":{"windDir":"南南西","windDeg":192,"windArrow":"⬆️","windSpeed":4.39,"windAlert":""},"tideBadge":null},{"key":"2026-07-20T17:00","hour":17,"label":"17:00","dateLabel":"7/20","isNight":false,"yahoo":{"icon":"☀️","desc":"晴れ","temp":33,"rainMm":0,"pop":7,"windDir":"南","windDeg":180,"windArrow":"⬆️","windSpeed":3,"windAlert":""},"umikaisei":{"wave":0.7,"waveFromFallback":false,"windDir":"南南西","windDeg":202.5,"windArrow":"↗️","windSpeed":7.8,"windAlert":"(面荒れ注意・オンショア)","tide":74,"tideTrend":"up"},"windy":{"wave":0.46,"wavePeriod":5.05,"windDir":"南南西","windDeg":196,"windArrow":"⬆️","windSpeed":3.96,"windAlert":""},"gfs":{"windDir":"南","windDeg":188,"windArrow":"⬆️","windSpeed":5.15,"windAlert":"(面荒れ注意・オンショア)"},"tideBadge":null},{"key":"2026-07-20T18:00","hour":18,"label":"18:00","dateLabel":"7/20","isNight":false,"yahoo":{"icon":"☀️","desc":"晴れ","temp":30,"rainMm":0,"pop":0,"windDir":"南","windDeg":180,"windArrow":"⬆️","windSpeed":3,"windAlert":""},"umikaisei":{"wave":0.7,"waveFromFallback":false,"windDir":"南南西","windDeg":202.5,"windArrow":"↗️","windSpeed":7.7,"windAlert":"(面荒れ注意・オンショア)","tide":97,"tideTrend":"up"},"windy":{"wave":0.48,"wavePeriod":4.9,"windDir":"南","windDeg":191,"windArrow":"⬆️","windSpeed":3.57,"windAlert":""},"gfs":{"windDir":"南","windDeg":187,"windArrow":"⬆️","windSpeed":4.23,"windAlert":""},"tideBadge":null},{"key":"2026-07-20T19:00","hour":19,"label":"19:00","dateLabel":"7/20","isNight":false,"yahoo":{"icon":"☀️","desc":"晴れ","temp":30,"rainMm":0,"pop":0,"windDir":"南","windDeg":180,"windArrow":"⬆️","windSpeed":3,"windAlert":""},"umikaisei":{"wave":0.7,"waveFromFallback":false,"windDir":"南南西","windDeg":202.5,"windArrow":"↗️","windSpeed":7.5,"windAlert":"(面荒れ注意・オンショア)","tide":119,"tideTrend":"up"},"windy":{"wave":0.48,"wavePeriod":4.85,"windDir":"南","windDeg":189,"windArrow":"⬆️","windSpeed":3.14,"windAlert":""},"gfs":{"windDir":"南","windDeg":180,"windArrow":"⬆️","windSpeed":3,"windAlert":""},"tideBadge":null},{"key":"2026-07-20T20:00","hour":20,"label":"20:00","dateLabel":"7/20","isNight":false,"yahoo":{"icon":"☀️","desc":"晴れ","temp":30,"rainMm":0,"pop":0,"windDir":"南","windDeg":180,"windArrow":"⬆️","windSpeed":3,"windAlert":""},"umikaisei":{"wave":0.7,"waveFromFallback":false,"windDir":"南南西","windDeg":202.5,"windArrow":"↗️","windSpeed":7.2,"windAlert":"(面荒れ注意・オンショア)","tide":135,"tideTrend":"up"},"windy":{"wave":0.48,"wavePeriod":4.95,"windDir":"南南西","windDeg":193,"windArrow":"⬆️","windSpeed":2.77,"windAlert":""},"gfs":{"windDir":"南","windDeg":189,"windArrow":"⬆️","windSpeed":2.53,"windAlert":""},"tideBadge":null},{"key":"2026-07-20T21:00","hour":21,"label":"21:00","dateLabel":"7/20","isNight":false,"yahoo":{"icon":"☀️","desc":"晴れ","temp":29,"rainMm":0,"pop":0,"windDir":"南南西","windDeg":202.5,"windArrow":"↗️","windSpeed":3,"windAlert":""},"umikaisei":{"wave":0.7,"waveFromFallback":false,"windDir":"南南西","windDeg":202.5,"windArrow":"↗️","windSpeed":7,"windAlert":"(面荒れ注意・オンショア)","tide":141,"tideTrend":"down"},"windy":{"wave":0.48,"wavePeriod":5,"windDir":"南","windDeg":185,"windArrow":"⬆️","windSpeed":2.31,"windAlert":""},"gfs":{"windDir":"南南西","windDeg":207,"windArrow":"↗️","windSpeed":3.13,"windAlert":""},"tideBadge":"🛑 満潮間近"},{"key":"2026-07-20T22:00","hour":22,"label":"22:00","dateLabel":"7/20","isNight":false,"yahoo":{"icon":"☀️","desc":"晴れ","temp":29,"rainMm":0,"pop":0,"windDir":"南南西","windDeg":202.5,"windArrow":"↗️","windSpeed":3,"windAlert":""},"umikaisei":{"wave":0.6,"waveFromFallback":false,"windDir":"南南西","windDeg":202.5,"windArrow":"↗️","windSpeed":7,"windAlert":"(面荒れ注意・オンショア)","tide":136,"tideTrend":"down"},"windy":{"wave":0.48,"wavePeriod":5.05,"windDir":"南","windDeg":185,"windArrow":"⬆️","windSpeed":2.21,"windAlert":""},"gfs":{"windDir":"南南西","windDeg":200,"windArrow":"⬆️","windSpeed":3.29,"windAlert":""},"tideBadge":null},{"key":"2026-07-20T23:00","hour":23,"label":"23:00","dateLabel":"7/20","isNight":false,"yahoo":{"icon":"☀️","desc":"晴れ","temp":29,"rainMm":0,"pop":0,"windDir":"南南西","windDeg":202.5,"windArrow":"↗️","windSpeed":3,"windAlert":""},"umikaisei":{"wave":0.6,"waveFromFallback":false,"windDir":"南南西","windDeg":202.5,"windArrow":"↗️","windSpeed":6.8,"windAlert":"(面荒れ注意・オンショア)","tide":123,"tideTrend":"down"},"windy":{"wave":0.46,"wavePeriod":5.15,"windDir":"南","windDeg":188,"windArrow":"⬆️","windSpeed":2.22,"windAlert":""},"gfs":{"windDir":"南南西","windDeg":197,"windArrow":"⬆️","windSpeed":3.13,"windAlert":""},"tideBadge":null},{"key":"2026-07-21T00:00","hour":0,"label":"00:00","dateLabel":"7/21","isNight":true,"yahoo":{"icon":"☀️","desc":"晴れ","temp":28,"rainMm":0,"pop":0,"windDir":"南南西","windDeg":202.5,"windArrow":"↗️","windSpeed":3,"windAlert":""},"umikaisei":{"wave":0.6,"waveFromFallback":false,"windDir":"南南西","windDeg":202.5,"windArrow":"↗️","windSpeed":6.9,"windAlert":"(面荒れ注意・オンショア)","tide":104,"tideTrend":"down"},"windy":{"wave":0.46,"wavePeriod":5.2,"windDir":"南","windDeg":191,"windArrow":"⬆️","windSpeed":2.14,"windAlert":""},"gfs":{"windDir":"南南西","windDeg":197,"windArrow":"⬆️","windSpeed":2.82,"windAlert":""},"tideBadge":null},{"key":"2026-07-21T01:00","hour":1,"label":"01:00","dateLabel":"7/21","isNight":true,"yahoo":{"icon":"☀️","desc":"晴れ","temp":28,"rainMm":0,"pop":0,"windDir":"南南西","windDeg":202.5,"windArrow":"↗️","windSpeed":3,"windAlert":""},"umikaisei":{"wave":0.6,"waveFromFallback":false,"windDir":"南南西","windDeg":202.5,"windArrow":"↗️","windSpeed":6.8,"windAlert":"(面荒れ注意・オンショア)","tide":86,"tideTrend":"down"},"windy":{"wave":0.44,"wavePeriod":5.25,"windDir":"南","windDeg":189,"windArrow":"⬆️","windSpeed":1.92,"windAlert":""},"gfs":{"windDir":"南","windDeg":191,"windArrow":"⬆️","windSpeed":2.65,"windAlert":""},"tideBadge":null},{"key":"2026-07-21T02:00","hour":2,"label":"02:00","dateLabel":"7/21","isNight":true,"yahoo":{"icon":"☀️","desc":"晴れ","temp":28,"rainMm":0,"pop":0,"windDir":"南南西","windDeg":202.5,"windArrow":"↗️","windSpeed":3,"windAlert":""},"umikaisei":{"wave":0.6,"waveFromFallback":false,"windDir":"南南西","windDeg":202.5,"windArrow":"↗️","windSpeed":6.8,"windAlert":"(面荒れ注意・オンショア)","tide":71,"tideTrend":"down"},"windy":{"wave":0.44,"wavePeriod":5.3,"windDir":"南","windDeg":190,"windArrow":"⬆️","windSpeed":1.73,"windAlert":""},"gfs":{"windDir":"南","windDeg":191,"windArrow":"⬆️","windSpeed":2.65,"windAlert":""},"tideBadge":"🟢 干潮間近"},{"key":"2026-07-21T03:00","hour":3,"label":"03:00","dateLabel":"7/21","isNight":true,"yahoo":{"icon":"☀️","desc":"晴れ","temp":27,"rainMm":0,"pop":0,"windDir":"南南西","windDeg":202.5,"windArrow":"↗️","windSpeed":2,"windAlert":""},"umikaisei":{"wave":0.6,"waveFromFallback":false,"windDir":"南南西","windDeg":202.5,"windArrow":"↗️","windSpeed":6.7,"windAlert":"(面荒れ注意・オンショア)","tide":65,"tideTrend":"up"},"windy":{"wave":0.42,"wavePeriod":5.35,"windDir":"南","windDeg":188,"windArrow":"⬆️","windSpeed":1.51,"windAlert":""},"gfs":{"windDir":"南","windDeg":185,"windArrow":"⬆️","windSpeed":2.31,"windAlert":""},"tideBadge":null},{"key":"2026-07-21T04:00","hour":4,"label":"04:00","dateLabel":"7/21","isNight":true,"yahoo":{"icon":"☀️","desc":"晴れ","temp":27,"rainMm":0,"pop":0,"windDir":"南南西","windDeg":202.5,"windArrow":"↗️","windSpeed":2,"windAlert":""},"umikaisei":{"wave":0.6,"waveFromFallback":false,"windDir":"南西","windDeg":225,"windArrow":"↗️","windSpeed":6.3,"windAlert":"(面荒れ注意・オンショア)","tide":67,"tideTrend":"up"},"windy":{"wave":0.4,"wavePeriod":5.45,"windDir":"南","windDeg":189,"windArrow":"⬆️","windSpeed":1.32,"windAlert":""},"gfs":{"windDir":"南","windDeg":180,"windArrow":"⬆️","windSpeed":1.9,"windAlert":""},"tideBadge":null},{"key":"2026-07-21T05:00","hour":5,"label":"05:00","dateLabel":"7/21","isNight":false,"yahoo":{"icon":"☀️","desc":"晴れ","temp":27,"rainMm":0,"pop":0,"windDir":"南南西","windDeg":202.5,"windArrow":"↗️","windSpeed":2,"windAlert":""},"umikaisei":{"wave":0.6,"waveFromFallback":false,"windDir":"南西","windDeg":225,"windArrow":"↗️","windSpeed":5.8,"windAlert":"(面荒れ注意・オンショア)","tide":78,"tideTrend":"up"},"windy":{"wave":0.4,"wavePeriod":5.55,"windDir":"南南西","windDeg":193,"windArrow":"⬆️","windSpeed":0.92,"windAlert":""},"gfs":{"windDir":"南","windDeg":175,"windArrow":"⬆️","windSpeed":1.1,"windAlert":""},"tideBadge":null},{"key":"2026-07-21T06:00","hour":6,"label":"06:00","dateLabel":"7/21","isNight":false,"yahoo":{"icon":"☀️","desc":"晴れ","temp":28,"rainMm":0,"pop":0,"windDir":"南西","windDeg":225,"windArrow":"↗️","windSpeed":1,"windAlert":""},"umikaisei":{"wave":0.6,"waveFromFallback":false,"windDir":"南西","windDeg":225,"windArrow":"↗️","windSpeed":4.7,"windAlert":"","tide":94,"tideTrend":"up"},"windy":{"wave":0.38,"wavePeriod":5.65,"windDir":"南","windDeg":180,"windArrow":"⬆️","windSpeed":0.8,"windAlert":""},"gfs":{"windDir":"南南東","windDeg":166,"windArrow":"⬆️","windSpeed":0.82,"windAlert":""},"tideBadge":null},{"key":"2026-07-21T07:00","hour":7,"label":"07:00","dateLabel":"7/21","isNight":false,"yahoo":{"icon":"☀️","desc":"晴れ","temp":28,"rainMm":0,"pop":0,"windDir":"南西","windDeg":225,"windArrow":"↗️","windSpeed":1,"windAlert":""},"umikaisei":{"wave":0.6,"waveFromFallback":false,"windDir":"南西","windDeg":225,"windArrow":"↗️","windSpeed":3.2,"windAlert":"","tide":110,"tideTrend":"up"},"windy":{"wave":0.38,"wavePeriod":5.75,"windDir":"南","windDeg":189,"windArrow":"⬆️","windSpeed":1.22,"windAlert":""},"gfs":{"windDir":"南","windDeg":171,"windArrow":"⬆️","windSpeed":0.61,"windAlert":""},"tideBadge":null},{"key":"2026-07-21T08:00","hour":8,"label":"08:00","dateLabel":"7/21","isNight":false,"yahoo":{"icon":"☀️","desc":"晴れ","temp":28,"rainMm":0,"pop":0,"windDir":"南西","windDeg":225,"windArrow":"↗️","windSpeed":1,"windAlert":""},"umikaisei":{"wave":0.5,"waveFromFallback":false,"windDir":"南西","windDeg":225,"windArrow":"↗️","windSpeed":1.9,"windAlert":"","tide":122,"tideTrend":"up"},"windy":{"wave":0.36,"wavePeriod":5.9,"windDir":"南南西","windDeg":200,"windArrow":"⬆️","windSpeed":2.02,"windAlert":""},"gfs":{"windDir":"南","windDeg":171,"windArrow":"⬆️","windSpeed":0.61,"windAlert":""},"tideBadge":"🛑 満潮間近"},{"key":"2026-07-21T09:00","hour":9,"label":"09:00","dateLabel":"7/21","isNight":false,"yahoo":{"icon":"☀️","desc":"晴れ","temp":32,"rainMm":0,"pop":0,"windDir":"南南西","windDeg":202.5,"windArrow":"↗️","windSpeed":2,"windAlert":""},"umikaisei":{"wave":0.5,"waveFromFallback":false,"windDir":"南南西","windDeg":202.5,"windArrow":"↗️","windSpeed":1.9,"windAlert":"","tide":127,"tideTrend":"down"},"windy":{"wave":0.36,"wavePeriod":6,"windDir":"南南西","windDeg":204,"windArrow":"↗️","windSpeed":2.42,"windAlert":""},"gfs":{"windDir":"南南東","windDeg":164,"windArrow":"⬆️","windSpeed":1.46,"windAlert":""},"tideBadge":null},{"key":"2026-07-21T10:00","hour":10,"label":"10:00","dateLabel":"7/21","isNight":false,"yahoo":{"icon":"☀️","desc":"晴れ","temp":32,"rainMm":0,"pop":7,"windDir":"南南西","windDeg":202.5,"windArrow":"↗️","windSpeed":2,"windAlert":""},"umikaisei":{"wave":0.4,"waveFromFallback":false,"windDir":"南南西","windDeg":202.5,"windArrow":"↗️","windSpeed":3.1,"windAlert":"","tide":123,"tideTrend":"down"},"windy":{"wave":0.36,"wavePeriod":6.05,"windDir":"南南西","windDeg":206,"windArrow":"↗️","windSpeed":2.55,"windAlert":""},"gfs":{"windDir":"南南東","windDeg":157,"windArrow":"↖️","windSpeed":2.06,"windAlert":""},"tideBadge":null},{"key":"2026-07-21T11:00","hour":11,"label":"11:00","dateLabel":"7/21","isNight":false,"yahoo":{"icon":"☀️","desc":"晴れ","temp":32,"rainMm":0,"pop":17,"windDir":"南南西","windDeg":202.5,"windArrow":"↗️","windSpeed":2,"windAlert":""},"umikaisei":{"wave":0.4,"waveFromFallback":false,"windDir":"南南西","windDeg":202.5,"windArrow":"↗️","windSpeed":4.2,"windAlert":"","tide":111,"tideTrend":"down"},"windy":{"wave":0.36,"wavePeriod":6.1,"windDir":"南南西","windDeg":201,"windArrow":"⬆️","windSpeed":2.79,"windAlert":""},"gfs":{"windDir":"南南東","windDeg":165,"windArrow":"⬆️","windSpeed":3.01,"windAlert":""},"tideBadge":null},{"key":"2026-07-21T12:00","hour":12,"label":"12:00","dateLabel":"7/21","isNight":false,"yahoo":{"icon":"☀️","desc":"晴れ","temp":33,"rainMm":0,"pop":31,"windDir":"南","windDeg":180,"windArrow":"⬆️","windSpeed":3,"windAlert":""},"umikaisei":{"wave":0.4,"waveFromFallback":false,"windDir":"南南西","windDeg":202.5,"windArrow":"↗️","windSpeed":5.4,"windAlert":"(面荒れ注意・オンショア)","tide":95,"tideTrend":"down"},"windy":{"wave":0.36,"wavePeriod":6.1,"windDir":"南南西","windDeg":194,"windArrow":"⬆️","windSpeed":3.3,"windAlert":""},"gfs":{"windDir":"南","windDeg":175,"windArrow":"⬆️","windSpeed":3.81,"windAlert":""},"tideBadge":null},{"key":"2026-07-21T13:00","hour":13,"label":"13:00","dateLabel":"7/21","isNight":false,"yahoo":{"icon":"☀️","desc":"晴れ","temp":33,"rainMm":0,"pop":53,"windDir":"南","windDeg":180,"windArrow":"⬆️","windSpeed":3,"windAlert":""},"umikaisei":{"wave":0.4,"waveFromFallback":false,"windDir":"南南西","windDeg":202.5,"windArrow":"↗️","windSpeed":6,"windAlert":"(面荒れ注意・オンショア)","tide":78,"tideTrend":"down"},"windy":{"wave":0.38,"wavePeriod":6,"windDir":"南南西","windDeg":197,"windArrow":"⬆️","windSpeed":3.86,"windAlert":""},"gfs":{"windDir":"南","windDeg":188,"windArrow":"⬆️","windSpeed":4.54,"windAlert":""},"tideBadge":null},{"key":"2026-07-21T14:00","hour":14,"label":"14:00","dateLabel":"7/21","isNight":false,"yahoo":{"icon":"☀️","desc":"晴れ","temp":33,"rainMm":0,"pop":79,"windDir":"南","windDeg":180,"windArrow":"⬆️","windSpeed":3,"windAlert":""},"umikaisei":{"wave":0.5,"waveFromFallback":false,"windDir":"南南西","windDeg":202.5,"windArrow":"↗️","windSpeed":6.3,"windAlert":"(面荒れ注意・オンショア)","tide":65,"tideTrend":"down"},"windy":{"wave":0.38,"wavePeriod":5.8,"windDir":"南南西","windDeg":196,"windArrow":"⬆️","windSpeed":4.37,"windAlert":""},"gfs":{"windDir":"南南西","windDeg":196,"windArrow":"⬆️","windSpeed":4.46,"windAlert":""},"tideBadge":"🟢 干潮間近"},{"key":"2026-07-21T15:00","hour":15,"label":"15:00","dateLabel":"7/21","isNight":false,"yahoo":{"icon":"☀️","desc":"晴れ","temp":33,"rainMm":0,"pop":92,"windDir":"南南西","windDeg":202.5,"windArrow":"↗️","windSpeed":3,"windAlert":""},"umikaisei":{"wave":0.5,"waveFromFallback":false,"windDir":"南南西","windDeg":202.5,"windArrow":"↗️","windSpeed":5.7,"windAlert":"(面荒れ注意・オンショア)","tide":59,"tideTrend":"up"},"windy":{"wave":0.4,"wavePeriod":5.65,"windDir":"南南西","windDeg":200,"windArrow":"⬆️","windSpeed":4.46,"windAlert":""},"gfs":{"windDir":"南南西","windDeg":198,"windArrow":"⬆️","windSpeed":4.11,"windAlert":""},"tideBadge":null},{"key":"2026-07-21T16:00","hour":16,"label":"16:00","dateLabel":"7/21","isNight":false,"yahoo":{"icon":"☀️","desc":"晴れ","temp":33,"rainMm":0,"pop":83,"windDir":"南南西","windDeg":202.5,"windArrow":"↗️","windSpeed":3,"windAlert":""},"umikaisei":{"wave":0.5,"waveFromFallback":false,"windDir":"南南西","windDeg":202.5,"windArrow":"↗️","windSpeed":5.2,"windAlert":"(面荒れ注意・オンショア)","tide":63,"tideTrend":"up"},"windy":{"wave":0.42,"wavePeriod":5.5,"windDir":"南南西","windDeg":201,"windArrow":"⬆️","windSpeed":4.18,"windAlert":""},"gfs":{"windDir":"南南西","windDeg":198,"windArrow":"⬆️","windSpeed":3.98,"windAlert":""},"tideBadge":null},{"key":"2026-07-21T17:00","hour":17,"label":"17:00","dateLabel":"7/21","isNight":false,"yahoo":{"icon":"☀️","desc":"晴れ","temp":33,"rainMm":0,"pop":62,"windDir":"南南西","windDeg":202.5,"windArrow":"↗️","windSpeed":3,"windAlert":""},"umikaisei":{"wave":0.6,"waveFromFallback":false,"windDir":"南南西","windDeg":202.5,"windArrow":"↗️","windSpeed":5.7,"windAlert":"(面荒れ注意・オンショア)","tide":75,"tideTrend":"up"},"windy":{"wave":0.42,"wavePeriod":5.35,"windDir":"南南西","windDeg":199,"windArrow":"⬆️","windSpeed":3.7,"windAlert":""},"gfs":{"windDir":"南南西","windDeg":195,"windArrow":"⬆️","windSpeed":4.15,"windAlert":""},"tideBadge":null},{"key":"2026-07-21T18:00","hour":18,"label":"18:00","dateLabel":"7/21","isNight":false,"yahoo":{"icon":"☀️","desc":"晴れ","temp":30,"rainMm":0,"pop":43,"windDir":"南南西","windDeg":202.5,"windArrow":"↗️","windSpeed":2,"windAlert":""},"umikaisei":{"wave":0.6,"waveFromFallback":false,"windDir":"南南西","windDeg":202.5,"windArrow":"↗️","windSpeed":6.3,"windAlert":"(面荒れ注意・オンショア)","tide":93,"tideTrend":"up"},"windy":{"wave":0.44,"wavePeriod":5.25,"windDir":"南南西","windDeg":194,"windArrow":"⬆️","windSpeed":2.98,"windAlert":""},"gfs":{"windDir":"南","windDeg":191,"windArrow":"⬆️","windSpeed":4.28,"windAlert":""},"tideBadge":null},{"key":"2026-07-21T19:00","hour":19,"label":"19:00","dateLabel":"7/21","isNight":false,"yahoo":{"icon":"☀️","desc":"晴れ","temp":30,"rainMm":0,"pop":29,"windDir":"南南西","windDeg":202.5,"windArrow":"↗️","windSpeed":2,"windAlert":""},"umikaisei":{"wave":0.7,"waveFromFallback":false,"windDir":"南南西","windDeg":202.5,"windArrow":"↗️","windSpeed":6.8,"windAlert":"(面荒れ注意・オンショア)","tide":112,"tideTrend":"up"},"windy":{"wave":0.44,"wavePeriod":5.25,"windDir":"南","windDeg":183,"windArrow":"⬆️","windSpeed":2,"windAlert":""},"gfs":{"windDir":"南","windDeg":184,"windArrow":"⬆️","windSpeed":4.01,"windAlert":""},"tideBadge":null},{"key":"2026-07-21T20:00","hour":20,"label":"20:00","dateLabel":"7/21","isNight":false,"yahoo":{"icon":"☀️","desc":"晴れ","temp":30,"rainMm":0,"pop":17,"windDir":"南南西","windDeg":202.5,"windArrow":"↗️","windSpeed":2,"windAlert":""},"umikaisei":{"wave":0.7,"waveFromFallback":false,"windDir":"南南西","windDeg":202.5,"windArrow":"↗️","windSpeed":6.8,"windAlert":"(面荒れ注意・オンショア)","tide":129,"tideTrend":"up"},"windy":{"wave":0.44,"wavePeriod":5.3,"windDir":"南","windDeg":186,"windArrow":"⬆️","windSpeed":2.01,"windAlert":""},"gfs":{"windDir":"南","windDeg":173,"windArrow":"⬆️","windSpeed":3.32,"windAlert":""},"tideBadge":null},{"key":"2026-07-21T21:00","hour":21,"label":"21:00","dateLabel":"7/21","isNight":false,"yahoo":{"icon":"☀️","desc":"晴れ","temp":29,"rainMm":0,"pop":8,"windDir":"南南西","windDeg":202.5,"windArrow":"↗️","windSpeed":2,"windAlert":""},"umikaisei":{"wave":0.7,"waveFromFallback":false,"windDir":"南南西","windDeg":202.5,"windArrow":"↗️","windSpeed":7.3,"windAlert":"(面荒れ注意・オンショア)","tide":138,"tideTrend":"up"},"windy":{"wave":0.44,"wavePeriod":5.4,"windDir":"南","windDeg":185,"windArrow":"⬆️","windSpeed":1.2,"windAlert":""},"gfs":{"windDir":"南","windDeg":169,"windArrow":"⬆️","windSpeed":2.55,"windAlert":""},"tideBadge":"🛑 満潮間近"},{"key":"2026-07-21T22:00","hour":22,"label":"22:00","dateLabel":"7/21","isNight":false,"yahoo":{"icon":"☀️","desc":"晴れ","temp":29,"rainMm":0,"pop":3,"windDir":"南南西","windDeg":202.5,"windArrow":"↗️","windSpeed":2,"windAlert":""},"umikaisei":{"wave":0.7,"waveFromFallback":false,"windDir":"南南西","windDeg":202.5,"windArrow":"↗️","windSpeed":7.6,"windAlert":"(面荒れ注意・オンショア)","tide":139,"tideTrend":"down"},"windy":{"wave":0.44,"wavePeriod":5.5,"windDir":"南東","windDeg":146,"windArrow":"↖️","windSpeed":0.36,"windAlert":""},"gfs":{"windDir":"南","windDeg":188,"windArrow":"⬆️","windSpeed":2.12,"windAlert":""},"tideBadge":null},{"key":"2026-07-21T23:00","hour":23,"label":"23:00","dateLabel":"7/21","isNight":false,"yahoo":{"icon":"☀️","desc":"晴れ","temp":29,"rainMm":0,"pop":1,"windDir":"南南西","windDeg":202.5,"windArrow":"↗️","windSpeed":2,"windAlert":""},"umikaisei":{"wave":0.7,"waveFromFallback":false,"windDir":"南南西","windDeg":202.5,"windArrow":"↗️","windSpeed":7.1,"windAlert":"(面荒れ注意・オンショア)","tide":130,"tideTrend":"down"},"windy":{"wave":0.42,"wavePeriod":5.65,"windDir":"南南東","windDeg":162,"windArrow":"⬆️","windSpeed":0.63,"windAlert":""},"gfs":{"windDir":"南南西","windDeg":196,"windArrow":"⬆️","windSpeed":2.18,"windAlert":""},"tideBadge":null},{"key":"2026-07-22T00:00","hour":0,"label":"00:00","dateLabel":"7/22","isNight":true,"yahoo":{"icon":"","desc":"","temp":null,"rainMm":null,"pop":0,"windDir":"--","windDeg":null,"windArrow":"","windSpeed":null,"windAlert":""},"umikaisei":{"wave":0.7,"waveFromFallback":false,"windDir":"南西","windDeg":225,"windArrow":"↗️","windSpeed":6.4,"windAlert":"(面荒れ注意・オンショア)","tide":114,"tideTrend":"down"},"windy":{"wave":0.42,"wavePeriod":5.75,"windDir":"南","windDeg":180,"windArrow":"⬆️","windSpeed":0.7,"windAlert":""},"gfs":{"windDir":"南南西","windDeg":198,"windArrow":"⬆️","windSpeed":1.9,"windAlert":""},"tideBadge":null},{"key":"2026-07-22T01:00","hour":1,"label":"01:00","dateLabel":"7/22","isNight":true,"yahoo":{"icon":"","desc":"","temp":null,"rainMm":null,"pop":0,"windDir":"--","windDeg":null,"windArrow":"","windSpeed":null,"windAlert":""},"umikaisei":{"wave":0.7,"waveFromFallback":false,"windDir":"南西","windDeg":225,"windArrow":"↗️","windSpeed":4.7,"windAlert":"","tide":95,"tideTrend":"down"},"windy":{"wave":0.42,"wavePeriod":5.85,"windDir":"南","windDeg":180,"windArrow":"⬆️","windSpeed":0.7,"windAlert":""},"gfs":{"windDir":"南南西","windDeg":207,"windArrow":"↗️","windSpeed":1.12,"windAlert":""},"tideBadge":null},{"key":"2026-07-22T02:00","hour":2,"label":"02:00","dateLabel":"7/22","isNight":true,"yahoo":{"icon":"","desc":"","temp":null,"rainMm":null,"pop":0,"windDir":"--","windDeg":null,"windArrow":"","windSpeed":null,"windAlert":""},"umikaisei":{"wave":0.6,"waveFromFallback":false,"windDir":"西南西","windDeg":247.5,"windArrow":"➡️","windSpeed":3.7,"windAlert":"","tide":77,"tideTrend":"down"},"windy":{"wave":0.4,"wavePeriod":5.95,"windDir":"南","windDeg":188,"windArrow":"⬆️","windSpeed":0.71,"windAlert":""},"gfs":{"windDir":"南西","windDeg":217,"windArrow":"↗️","windSpeed":0.5,"windAlert":""},"tideBadge":"🟢 干潮間近"},{"key":"2026-07-22T03:00","hour":3,"label":"03:00","dateLabel":"7/22","isNight":true,"yahoo":{"icon":"","desc":"","temp":null,"rainMm":null,"pop":0,"windDir":"--","windDeg":null,"windArrow":"","windSpeed":null,"windAlert":""},"umikaisei":{"wave":0.6,"waveFromFallback":false,"windDir":"西","windDeg":270,"windArrow":"➡️","windSpeed":3.4,"windAlert":"","tide":64,"tideTrend":"down"},"windy":{"wave":0.4,"wavePeriod":6.05,"windDir":"南","windDeg":187,"windArrow":"⬆️","windSpeed":0.81,"windAlert":""},"gfs":{"windDir":"西北西","windDeg":301,"windArrow":"↘️","windSpeed":0.58,"windAlert":""},"tideBadge":null},{"key":"2026-07-22T04:00","hour":4,"label":"04:00","dateLabel":"7/22","isNight":true,"yahoo":{"icon":"","desc":"","temp":null,"rainMm":null,"pop":0,"windDir":"--","windDeg":null,"windArrow":"","windSpeed":null,"windAlert":""},"umikaisei":{"wave":0.6,"waveFromFallback":false,"windDir":"西北西","windDeg":292.5,"windArrow":"↘️","windSpeed":2.6,"windAlert":"","tide":58,"tideTrend":"up"},"windy":{"wave":0.4,"wavePeriod":6.05,"windDir":"南","windDeg":187,"windArrow":"⬆️","windSpeed":0.81,"windAlert":""},"gfs":{"windDir":"北北西","windDeg":335,"windArrow":"↘️","windSpeed":1.43,"windAlert":""},"tideBadge":null},{"key":"2026-07-22T05:00","hour":5,"label":"05:00","dateLabel":"7/22","isNight":false,"yahoo":{"icon":"","desc":"","temp":null,"rainMm":null,"pop":0,"windDir":"--","windDeg":null,"windArrow":"","windSpeed":null,"windAlert":""},"umikaisei":{"wave":0.5,"waveFromFallback":false,"windDir":"北西","windDeg":315,"windArrow":"↘️","windSpeed":2,"windAlert":"","tide":61,"tideTrend":"up"},"windy":{"wave":0.4,"wavePeriod":6.05,"windDir":"南","windDeg":188,"windArrow":"⬆️","windSpeed":0.71,"windAlert":""},"gfs":{"windDir":"北","windDeg":2,"windArrow":"⬇️","windSpeed":2.4,"windAlert":""},"tideBadge":null},{"key":"2026-07-22T06:00","hour":6,"label":"06:00","dateLabel":"7/22","isNight":false,"yahoo":{"icon":"","desc":"","temp":null,"rainMm":null,"pop":0,"windDir":"--","windDeg":null,"windArrow":"","windSpeed":null,"windAlert":""},"umikaisei":{"wave":0.5,"waveFromFallback":false,"windDir":"北","windDeg":0,"windArrow":"⬇️","windSpeed":2.2,"windAlert":"","tide":72,"tideTrend":"up"},"windy":{"wave":0.4,"wavePeriod":6.05,"windDir":"南","windDeg":180,"windArrow":"⬆️","windSpeed":0.4,"windAlert":""},"gfs":{"windDir":"北北東","windDeg":25,"windArrow":"↙️","windSpeed":2.64,"windAlert":""},"tideBadge":null},{"key":"2026-07-22T07:00","hour":7,"label":"07:00","dateLabel":"7/22","isNight":false,"yahoo":{"icon":"","desc":"","temp":null,"rainMm":null,"pop":0,"windDir":"--","windDeg":null,"windArrow":"","windSpeed":null,"windAlert":""},"umikaisei":{"wave":0.5,"waveFromFallback":false,"windDir":"北北東","windDeg":22.5,"windArrow":"↙️","windSpeed":2.9,"windAlert":"","tide":86,"tideTrend":"up"},"windy":{"wave":0.4,"wavePeriod":6.05,"windDir":"南","windDeg":189,"windArrow":"⬆️","windSpeed":0.61,"windAlert":""},"gfs":{"windDir":"北東","windDeg":47,"windArrow":"↙️","windSpeed":2.33,"windAlert":""},"tideBadge":null},{"key":"2026-07-22T08:00","hour":8,"label":"08:00","dateLabel":"7/22","isNight":false,"yahoo":{"icon":"","desc":"","temp":null,"rainMm":null,"pop":0,"windDir":"--","windDeg":null,"windArrow":"","windSpeed":null,"windAlert":""},"umikaisei":{"wave":0.4,"waveFromFallback":false,"windDir":"北東","windDeg":45,"windArrow":"↙️","windSpeed":4.1,"windAlert":"","tide":101,"tideTrend":"up"},"windy":{"wave":0.38,"wavePeriod":6.1,"windDir":"南南西","windDeg":195,"windArrow":"⬆️","windSpeed":1.55,"windAlert":""},"gfs":{"windDir":"東北東","windDeg":63,"windArrow":"↙️","windSpeed":2.01,"windAlert":""},"tideBadge":"🛑 満潮間近"},{"key":"2026-07-22T09:00","hour":9,"label":"09:00","dateLabel":"7/22","isNight":false,"yahoo":{"icon":"","desc":"","temp":null,"rainMm":null,"pop":0,"windDir":"--","windDeg":null,"windArrow":"","windSpeed":null,"windAlert":""},"umikaisei":{"wave":0.4,"waveFromFallback":false,"windDir":"東北東","windDeg":67.5,"windArrow":"⬅️","windSpeed":3.8,"windAlert":"","tide":112,"tideTrend":"up"},"windy":{"wave":0.38,"wavePeriod":6.1,"windDir":"南南西","windDeg":207,"windArrow":"↗️","windSpeed":2.01,"windAlert":""},"gfs":{"windDir":"東","windDeg":93,"windArrow":"⬅️","windSpeed":1.8,"windAlert":""},"tideBadge":null},{"key":"2026-07-22T10:00","hour":10,"label":"10:00","dateLabel":"7/22","isNight":false,"yahoo":{"icon":"","desc":"","temp":null,"rainMm":null,"pop":6,"windDir":"--","windDeg":null,"windArrow":"","windSpeed":null,"windAlert":""},"umikaisei":{"wave":0.4,"waveFromFallback":false,"windDir":"東北東","windDeg":67.5,"windArrow":"⬅️","windSpeed":3,"windAlert":"","tide":118,"tideTrend":"down"},"windy":{"wave":0.38,"wavePeriod":6.1,"windDir":"南南西","windDeg":208,"windArrow":"↗️","windSpeed":2.37,"windAlert":""},"gfs":{"windDir":"南東","windDeg":131,"windArrow":"↖️","windSpeed":1.98,"windAlert":""},"tideBadge":null},{"key":"2026-07-22T11:00","hour":11,"label":"11:00","dateLabel":"7/22","isNight":false,"yahoo":{"icon":"","desc":"","temp":null,"rainMm":null,"pop":14,"windDir":"--","windDeg":null,"windArrow":"","windSpeed":null,"windAlert":""},"umikaisei":{"wave":0.4,"waveFromFallback":false,"windDir":"東","windDeg":90,"windArrow":"⬅️","windSpeed":1.3,"windAlert":"","tide":116,"tideTrend":"down"},"windy":{"wave":0.38,"wavePeriod":6.05,"windDir":"南南西","windDeg":201,"windArrow":"⬆️","windSpeed":3.01,"windAlert":""},"gfs":{"windDir":"南","windDeg":169,"windArrow":"⬆️","windSpeed":2.65,"windAlert":""},"tideBadge":null},{"key":"2026-07-22T12:00","hour":12,"label":"12:00","dateLabel":"7/22","isNight":false,"yahoo":{"icon":"","desc":"","temp":null,"rainMm":null,"pop":27,"windDir":"--","windDeg":null,"windArrow":"","windSpeed":null,"windAlert":""},"umikaisei":{"wave":0.3,"waveFromFallback":false,"windDir":"南西","windDeg":225,"windArrow":"↗️","windSpeed":4.3,"windAlert":"","tide":108,"tideTrend":"down"},"windy":{"wave":0.38,"wavePeriod":6,"windDir":"南南西","windDeg":199,"windArrow":"⬆️","windSpeed":3.38,"windAlert":""},"gfs":{"windDir":"南","windDeg":188,"windArrow":"⬆️","windSpeed":3.63,"windAlert":""},"tideBadge":null},{"key":"2026-07-22T13:00","hour":13,"label":"13:00","dateLabel":"7/22","isNight":false,"yahoo":{"icon":"","desc":"","temp":null,"rainMm":null,"pop":49,"windDir":"--","windDeg":null,"windArrow":"","windSpeed":null,"windAlert":""},"umikaisei":{"wave":0.3,"waveFromFallback":false,"windDir":"南西","windDeg":225,"windArrow":"↗️","windSpeed":5.2,"windAlert":"(面荒れ注意・オンショア)","tide":97,"tideTrend":"down"},"windy":{"wave":0.4,"wavePeriod":5.85,"windDir":"南南西","windDeg":195,"windArrow":"⬆️","windSpeed":3.93,"windAlert":""},"gfs":{"windDir":"南","windDeg":185,"windArrow":"⬆️","windSpeed":4.32,"windAlert":""},"tideBadge":null},{"key":"2026-07-22T14:00","hour":14,"label":"14:00","dateLabel":"7/22","isNight":false,"yahoo":{"icon":"","desc":"","temp":null,"rainMm":null,"pop":76,"windDir":"--","windDeg":null,"windArrow":"","windSpeed":null,"windAlert":""},"umikaisei":{"wave":0.4,"waveFromFallback":false,"windDir":"南西","windDeg":225,"windArrow":"↗️","windSpeed":5.1,"windAlert":"(面荒れ注意・オンショア)","tide":85,"tideTrend":"down"},"windy":{"wave":0.4,"wavePeriod":5.6,"windDir":"南南西","windDeg":196,"windArrow":"⬆️","windSpeed":4.05,"windAlert":""},"gfs":{"windDir":"南南西","windDeg":192,"windArrow":"⬆️","windSpeed":5,"windAlert":"(面荒れ注意・オンショア)"},"tideBadge":"🟢 干潮間近"},{"key":"2026-07-22T15:00","hour":15,"label":"15:00","dateLabel":"7/22","isNight":false,"yahoo":{"icon":"","desc":"","temp":null,"rainMm":null,"pop":90,"windDir":"--","windDeg":null,"windArrow":"","windSpeed":null,"windAlert":""},"umikaisei":{"wave":0.4,"waveFromFallback":false,"windDir":"南南西","windDeg":202.5,"windArrow":"↗️","windSpeed":5.3,"windAlert":"(面荒れ注意・オンショア)","tide":77,"tideTrend":"down"},"windy":{"wave":0.42,"wavePeriod":5.45,"windDir":"南南西","windDeg":196,"windArrow":"⬆️","windSpeed":3.96,"windAlert":""},"gfs":{"windDir":"南南西","windDeg":194,"windArrow":"⬆️","windSpeed":4.54,"windAlert":""},"tideBadge":null},{"key":"2026-07-22T16:00","hour":16,"label":"16:00","dateLabel":"7/22","isNight":false,"yahoo":{"icon":"","desc":"","temp":null,"rainMm":null,"pop":82,"windDir":"--","windDeg":null,"windArrow":"","windSpeed":null,"windAlert":""},"umikaisei":{"wave":0.42,"waveFromFallback":true,"windDir":"--","windDeg":194,"windArrow":"⬆️","windSpeed":3.81,"windAlert":"","tide":76,"tideTrend":"up"},"windy":{"wave":0.42,"wavePeriod":5.4,"windDir":"南南西","windDeg":194,"windArrow":"⬆️","windSpeed":3.81,"windAlert":""},"gfs":{"windDir":"南","windDeg":187,"windArrow":"⬆️","windSpeed":4.84,"windAlert":""},"tideBadge":null},{"key":"2026-07-22T17:00","hour":17,"label":"17:00","dateLabel":"7/22","isNight":false,"yahoo":{"icon":"","desc":"","temp":null,"rainMm":null,"pop":61,"windDir":"--","windDeg":null,"windArrow":"","windSpeed":null,"windAlert":""},"umikaisei":{"wave":0.44,"waveFromFallback":true,"windDir":"--","windDeg":189,"windArrow":"⬆️","windSpeed":3.65,"windAlert":"","tide":81,"tideTrend":"up"},"windy":{"wave":0.44,"wavePeriod":5.4,"windDir":"南","windDeg":189,"windArrow":"⬆️","windSpeed":3.65,"windAlert":""},"gfs":{"windDir":"南南西","windDeg":194,"windArrow":"⬆️","windSpeed":4.63,"windAlert":""},"tideBadge":null},{"key":"2026-07-22T18:00","hour":18,"label":"18:00","dateLabel":"7/22","isNight":false,"yahoo":{"icon":"","desc":"","temp":null,"rainMm":null,"pop":41,"windDir":"--","windDeg":null,"windArrow":"","windSpeed":null,"windAlert":""},"umikaisei":{"wave":0.44,"waveFromFallback":true,"windDir":"--","windDeg":188,"windArrow":"⬆️","windSpeed":2.83,"windAlert":"","tide":92,"tideTrend":"up"},"windy":{"wave":0.44,"wavePeriod":5.4,"windDir":"南","windDeg":188,"windArrow":"⬆️","windSpeed":2.83,"windAlert":""},"gfs":{"windDir":"南南西","windDeg":194,"windArrow":"⬆️","windSpeed":3.81,"windAlert":""},"tideBadge":null},{"key":"2026-07-22T19:00","hour":19,"label":"19:00","dateLabel":"7/22","isNight":false,"yahoo":{"icon":"","desc":"","temp":null,"rainMm":null,"pop":26,"windDir":"--","windDeg":null,"windArrow":"","windSpeed":null,"windAlert":""},"umikaisei":{"wave":0.44,"waveFromFallback":true,"windDir":"--","windDeg":177,"windArrow":"⬆️","windSpeed":2,"windAlert":"","tide":107,"tideTrend":"up"},"windy":{"wave":0.44,"wavePeriod":5.4,"windDir":"南","windDeg":177,"windArrow":"⬆️","windSpeed":2,"windAlert":""},"gfs":{"windDir":"南","windDeg":175,"windArrow":"⬆️","windSpeed":3.31,"windAlert":""},"tideBadge":null},{"key":"2026-07-22T20:00","hour":20,"label":"20:00","dateLabel":"7/22","isNight":false,"yahoo":{"icon":"","desc":"","temp":null,"rainMm":null,"pop":12,"windDir":"--","windDeg":null,"windArrow":"","windSpeed":null,"windAlert":""},"umikaisei":{"wave":0.46,"waveFromFallback":true,"windDir":"--","windDeg":165,"windArrow":"⬆️","windSpeed":1.55,"windAlert":"","tide":123,"tideTrend":"up"},"windy":{"wave":0.46,"wavePeriod":5.4,"windDir":"南南東","windDeg":165,"windArrow":"⬆️","windSpeed":1.55,"windAlert":""},"gfs":{"windDir":"南南東","windDeg":153,"windArrow":"↖️","windSpeed":3.8,"windAlert":""},"tideBadge":null},{"key":"2026-07-22T21:00","hour":21,"label":"21:00","dateLabel":"7/22","isNight":false,"yahoo":{"icon":"","desc":"","temp":null,"rainMm":null,"pop":2,"windDir":"--","windDeg":null,"windArrow":"","windSpeed":null,"windAlert":""},"umikaisei":{"wave":0.46,"waveFromFallback":true,"windDir":"--","windDeg":160,"windArrow":"⬆️","windSpeed":1.49,"windAlert":"","tide":134,"tideTrend":"up"},"windy":{"wave":0.46,"wavePeriod":5.4,"windDir":"南南東","windDeg":160,"windArrow":"⬆️","windSpeed":1.49,"windAlert":""},"gfs":{"windDir":"南","windDeg":172,"windArrow":"⬆️","windSpeed":2.22,"windAlert":""},"tideBadge":"🛑 満潮間近"},{"key":"2026-07-22T22:00","hour":22,"label":"22:00","dateLabel":"7/22","isNight":false,"yahoo":{"icon":"","desc":"","temp":null,"rainMm":null,"pop":0,"windDir":"--","windDeg":null,"windArrow":"","windSpeed":null,"windAlert":""},"umikaisei":{"wave":0.46,"waveFromFallback":true,"windDir":"--","windDeg":165,"windArrow":"⬆️","windSpeed":1.14,"windAlert":"","tide":139,"tideTrend":"down"},"windy":{"wave":0.46,"wavePeriod":5.4,"windDir":"南南東","windDeg":165,"windArrow":"⬆️","windSpeed":1.14,"windAlert":""},"gfs":{"windDir":"東南東","windDeg":112,"windArrow":"⬅️","windSpeed":1.08,"windAlert":""},"tideBadge":null},{"key":"2026-07-22T23:00","hour":23,"label":"23:00","dateLabel":"7/22","isNight":false,"yahoo":{"icon":"","desc":"","temp":null,"rainMm":null,"pop":1,"windDir":"--","windDeg":null,"windArrow":"","windSpeed":null,"windAlert":""},"umikaisei":{"wave":0.48,"waveFromFallback":true,"windDir":"--","windDeg":174,"windArrow":"⬆️","windSpeed":0.91,"windAlert":"","tide":136,"tideTrend":"down"},"windy":{"wave":0.48,"wavePeriod":5.4,"windDir":"南","windDeg":174,"windArrow":"⬆️","windSpeed":0.91,"windAlert":""},"gfs":{"windDir":"東南東","windDeg":122,"windArrow":"↖️","windSpeed":1.89,"windAlert":""},"tideBadge":null},{"key":"2026-07-23T00:00","hour":0,"label":"00:00","dateLabel":"7/23","isNight":true,"yahoo":{"icon":"","desc":"","temp":null,"rainMm":null,"pop":2,"windDir":"--","windDeg":null,"windArrow":"","windSpeed":null,"windAlert":""},"umikaisei":{"wave":0.48,"waveFromFallback":true,"windDir":"--","windDeg":180,"windArrow":"⬆️","windSpeed":0.4,"windAlert":"","tide":124,"tideTrend":"down"},"windy":{"wave":0.48,"wavePeriod":5.45,"windDir":"南","windDeg":180,"windArrow":"⬆️","windSpeed":0.4,"windAlert":""},"gfs":{"windDir":"南東","windDeg":129,"windArrow":"↖️","windSpeed":1.42,"windAlert":""},"tideBadge":null},{"key":"2026-07-23T01:00","hour":1,"label":"01:00","dateLabel":"7/23","isNight":true,"yahoo":{"icon":"","desc":"","temp":null,"rainMm":null,"pop":2,"windDir":"--","windDeg":null,"windArrow":"","windSpeed":null,"windAlert":""},"umikaisei":{"wave":0.48,"waveFromFallback":true,"windDir":"--","windDeg":135,"windArrow":"↖️","windSpeed":0.57,"windAlert":"","tide":107,"tideTrend":"down"},"windy":{"wave":0.48,"wavePeriod":5.5,"windDir":"南東","windDeg":135,"windArrow":"↖️","windSpeed":0.57,"windAlert":""},"gfs":{"windDir":"東北東","windDeg":75,"windArrow":"⬅️","windSpeed":1.96,"windAlert":""},"tideBadge":null},{"key":"2026-07-23T02:00","hour":2,"label":"02:00","dateLabel":"7/23","isNight":true,"yahoo":{"icon":"","desc":"","temp":null,"rainMm":null,"pop":2,"windDir":"--","windDeg":null,"windArrow":"","windSpeed":null,"windAlert":""},"umikaisei":{"wave":0.46,"waveFromFallback":true,"windDir":"--","windDeg":166,"windArrow":"⬆️","windSpeed":0.41,"windAlert":"","tide":88,"tideTrend":"down"},"windy":{"wave":0.46,"wavePeriod":5.6,"windDir":"南南東","windDeg":166,"windArrow":"⬆️","windSpeed":0.41,"windAlert":""},"gfs":{"windDir":"東北東","windDeg":69,"windArrow":"⬅️","windSpeed":1.93,"windAlert":""},"tideBadge":"🟢 干潮間近"},{"key":"2026-07-23T03:00","hour":3,"label":"03:00","dateLabel":"7/23","isNight":true,"yahoo":{"icon":"","desc":"","temp":null,"rainMm":null,"pop":2,"windDir":"--","windDeg":null,"windArrow":"","windSpeed":null,"windAlert":""},"umikaisei":{"wave":0.46,"waveFromFallback":true,"windDir":"--","windDeg":180,"windArrow":"⬆️","windSpeed":0.5,"windAlert":"","tide":70,"tideTrend":"down"},"windy":{"wave":0.46,"wavePeriod":5.7,"windDir":"南","windDeg":180,"windArrow":"⬆️","windSpeed":0.5,"windAlert":""},"gfs":{"windDir":"北東","windDeg":43,"windArrow":"↙️","windSpeed":1.91,"windAlert":""},"tideBadge":null}],"sources":{"yahoo":true,"umikaisei":true,"umikaiseiTide":true,"openMeteo":true},"debug":{"hours":85,"tideHighs":2}}}}